Workbook

Sheet Start Here
B2: DSA Master Revision Sheet - v4
B3: Built for Kartik | C++ / STL | placement + internship prep
B5: The one rule | C5: Only the Master tab is editable (plus the yellow cells on Plan and Dashboard). Everything else calculates itself.
C6: You fill in: Status, Confidence, Attempts, Last Revised, Notes. Nothing else.
B8: Tier - read this first | C8: 922 questions is not a plan, it is a wall. The Tier column splits them into three tracks, and the Step column orders them: work down it, and see Path Stages for the ranges.
C9: Core (373) - at least two problems per pattern, every pattern in the sheet. Finish this and you have touched every idea an interview can ask. This is your actual target.
C10: Depth - extra reps on patterns you are still shaky on. Do these per topic, only where Pattern Radar says Weak.
C11: Stretch - Hard problems and Advanced DS (segment tree, Fenwick, sweep line, sparse table). Not placement-critical. Leave them until Core is above 80%.
C12: Tier is a dropdown, so you can promote or demote anything. If a Depth problem turns out to be the one that taught you the pattern, mark it Core.
B14: Status values (dropdown) | C14: Not Started - haven't opened it yet.
C15: Attempted - tried, could not finish. Auto-flagged DUE until you clear it.
C16: Solved - solved it, but needed a hint or the editorial.
C17: Mastered - solved clean, from scratch, and can re-derive the approach out loud.
C18: Revisit - solved once, but it faded. Also auto-flagged DUE.
C19: Done = Solved + Mastered everywhere in this workbook.
B21: Confidence (1-5 dropdown) - now it actually does something | C21: 1 = no idea why it works. 3 = can code it with effort. 5 = can explain the invariant and the complexity without thinking.
C22: Confidence drives the revision gap: 1 -> 2 days, 2 -> 4, 3 -> 7, 4 -> 21, 5 -> 45. Change those gaps on the Dashboard if they don't suit you.
C23: Be harsh. Inflated confidence just means the sheet stops showing you the thing you can't do.
B25: How revision works now | C25: Set Last Revised when you solve or re-solve something. Next Revision fills in by itself from your Confidence.
C26: The Due? column says DUE when that date arrives, or immediately if the status is Attempted or Revisit.
C27: Your daily routine: filter Due? = DUE on the Master tab. That is the whole revision decision. No judgement calls.
C28: Dashboard shows the live due count. If it climbs past about 15, stop taking new problems for a day and clear it.
B30: Pattern Radar - the honest tab | C30: Per-pattern totals, done count and average confidence across all 168 patterns.
C31: Verdict: Untouched (nothing solved), Weak (avg confidence 3 or below), Solid (above 3).
C32: Filter Verdict = Weak before an interview. That list is exactly what you will get caught on.
C33: Topic-level progress lies - 80% of Graphs done still means you have never written Dijkstra. Pattern level does not lie.
B35: Plan tab | C35: Enter a start date and a realistic problems-per-day number. It gives you six phase deadlines off the Core count.
C36: Order is not negotiable: Recursion and Backtracking come before DP, because DP is memoised recursion. Skipping that is why DP feels impossible.
B38: Weekly ritual (15 minutes, Sunday) | C38: 1. Pick 4 random Mastered problems, re-solve them timed. Anything that breaks drops to Revisit.
C39: 2. Open Pattern Radar, filter Weak, pick one pattern for the coming week.
C40: 3. Check Plan tab - are you ahead or behind? Adjust the pace cell, not the ambition.
B42: A note on the links | C42: LeetCode entries link straight to the problem. Non-LeetCode entries use a search link, because GFG problem IDs change over time and a hardcoded ID goes dead.
C43: When you open a search link and land on the right problem, paste the real URL over it. The sheet gets more accurate as you use it.
B45: Example row (delete once you start) | C45: Two Sum | Tier: Core | Status: Mastered | Confidence: 5 | Attempts: 2 | Last Revised: 2026-09-13 | Notes: hashmap of complement, one pass, O(n)

Sheet Path Stages
A1: Stage | B1: Steps | C1: Problems | D1: Easy | E1: Medium | F1: Hard | G1: Topics covered
A2: 1. Foundations - Core | B2: 1-87 | C2: 87 | D2: 52 | E2: 34 | F2: 1 | G2: Basics & Recursion, Arrays & Two Pointers, Sorting & Cyclic Sort, Hashing, Prefix Sum & Kadane, Sliding Window
A3: 1. Foundations - Depth | B3: 88-153 | C3: 66 | D3: 14 | E3: 51 | F3: 1 | G3: Arrays & Two Pointers, Sorting & Cyclic Sort, Hashing, Prefix Sum & Kadane, Sliding Window
A4: 1. Foundations - Stretch | B4: 154-163 | C4: 10 | D4: 0 | E4: 1 | F4: 9 | G4: Arrays & Two Pointers, Sorting & Cyclic Sort, Hashing, Prefix Sum & Kadane, Sliding Window
A5: 2. Search, Strings & Math - Core | B5: 164-257 | C5: 94 | D5: 63 | E5: 31 | F5: 0 | G5: Binary Search, Strings, Bit Manipulation, Math & Number Theory, Matrix / 2D
A6: 2. Search, Strings & Math - Depth | B6: 258-328 | C6: 71 | D6: 8 | E6: 58 | F6: 5 | G6: Binary Search, Strings, Bit Manipulation, Math & Number Theory, Matrix / 2D
A7: 2. Search, Strings & Math - Stretch | B7: 329-348 | C7: 20 | D7: 0 | E7: 0 | F7: 20 | G7: Binary Search, Strings, Bit Manipulation, Math & Number Theory
A8: 3. Linear DS - Core | B8: 349-394 | C8: 46 | D8: 20 | E8: 24 | F8: 2 | G8: Linked List, Stack & Queue, Heap & Priority Queue
A9: 3. Linear DS - Depth | B9: 395-443 | C9: 49 | D9: 1 | E9: 48 | F9: 0 | G9: Linked List, Stack & Queue, Heap & Priority Queue
A10: 3. Linear DS - Stretch | B10: 444-463 | C10: 20 | D10: 0 | E10: 0 | F10: 20 | G10: Linked List, Stack & Queue, Heap & Priority Queue
A11: 4. Greedy & Backtracking - Core | B11: 464-507 | C11: 44 | D11: 15 | E11: 29 | F11: 0 | G11: Intervals, Greedy, Backtracking
A12: 4. Greedy & Backtracking - Depth | B12: 508-552 | C12: 45 | D12: 0 | E12: 44 | F12: 1 | G12: Intervals, Greedy, Backtracking
A13: 4. Greedy & Backtracking - Stretch | B13: 553-577 | C13: 25 | D13: 0 | E13: 0 | F13: 25 | G13: Intervals, Greedy, Backtracking
... A19: 6. DP & Closers - Stretch | B19: 870-917 | C19: 48 | D19: 0 | E19: 0 | F19: 48 | G19: Dynamic Programming, Design, Advanced DS

Sheet Plan
B2: Phase Plan
B3: Fill the two yellow cells. Dates recalculate themselves. Core-track only - Depth and Stretch sit outside this timeline.
B5: Start date | C5: 2026-09-15 | D5: <- your realistic pace, not your ambitious one
B6: Core problems per day | C6: 2
B8: Phase | C8: Topics covered | D8: Core Qs | E8: Cumulative | F8: Days | G8: Target finish | H8: Done | I8: %
B9: Phase 1 - Foundations | C9: 01 - 05: Basics & Recursion, Arrays & Two Pointers, Sliding Window, Prefix Sum & Kadane, Sorting & Cyclic Sort | D9: =COUNTIFS(Master!$C$2:$C$918,"01. Basics & Recursion",Master!$G$2:$G$918,"Core")+COUNTIFS(Master!$C$2:$C$918,"02. Arrays & Two Pointers",Master!$G$2:$G$918,"Core")+COUNTIFS(Master!$C$2:$C$918,"03. Sliding Window",Master!$G$2:$G$918,"Core")+COUNTIFS(Master!$C$2:$C$918,"04. Prefix Sum & Kadane",Master!$G$2:$G$918,"Core")+COUNTIFS(Master!$C$2:$C$918,"05. Sorting & Cyclic Sort",Master!$G$2:$G$918,"Core") | E9: =$D9 | F9: =ROUNDUP($E9/$C$6,0) | G9: =$C$5+$F9 | H9: =COUNTIFS(Master!$C$2:$C$918,"01. Basics & Recursion",Master!$G$2:$G$918,"Core",Master!$J$2:$J$918,"Solved")+COUNTIFS(Master!$C$2:$C$918,"01. Basics & Recursion",Master!$G$2:$G$918,"Core",Master!$J$2:$J$918,"Mastered")+COUNTIFS(Master!$C$2:$C$918,"02. Arrays & Two Pointers",Master!$G$2:$G$918,"Core",Master!$J$2:$J$918,"Solved")+COUNTIFS(Master!$C$2:$C$918,"02. Arrays & Two Pointers",Master!$G$2:$G$918,"Core",Master!$J$2:$J$918,"Mastered")+COUNTIFS(Master!$C$2:$C$918,"03. Sliding Window",Master!$G$2:$G$918,"Core",Master!$J$2:$J$918,"Solved")+COUNTIFS(Master!$C$2:$C$918,"03. Sliding Window",Master!$G$2:$G$918,"Core",Master!$J$2:$J$918,"Mastered")+COUNTIFS(Master!$C$2:$C$918,"04. Prefix Sum & Kadane",Master!$G$2:$G$918,"Core",Master!$J$2:$J$918,"Solved")+COUNTIFS(Master!$C$2:$C$918,"04. Prefix Sum & Kadane",Master!$G$2:$G$918,"Core",Master!$J$2:$J$918,"Mastered")+COUNTIFS(Master!$C$2:$C$918,"05. Sorting & Cyclic Sort",Master!$G$2:$G$918,"Core",Master!$J$2:$J$918,"Solved")+COUNTIFS(Master!$C$2:$C$918,"05. Sorting & Cyclic Sort",Master!$G$2:$G$918,"Core",Master!$J$2:$J$918,"Mastered") | I9: =IFERROR($H9/$D9,0)
B10: Phase 2 - Search & Strings | C10: 06 - 09: Binary Search, Strings, Hashing, Matrix / 2D | D10: =COUNTIFS(Master!$C$2:$C$918,"06. Binary Search",Master!$G$2:$G$918,"Core")+COUNTIFS(Master!$C$2:$C$918,"07. Strings",Master!$G$2:$G$918,"Core")+COUNTIFS(Master!$C$2:$C$918,"08. Hashing",Master!$G$2:$G$918,"Core")+COUNTIFS(Master!$C$2:$C$918,"09. Matrix / 2D",Master!$G$2:$G$918,"Core") | E10: =$E9+$D10 | F10: =ROUNDUP($E10/$C$6,0) | G10: =$C$5+$F10 | H10: =COUNTIFS(Master!$C$2:$C$918,"06. Binary Search",Master!$G$2:$G$918,"Core",Master!$J$2:$J$918,"Solved")+COUNTIFS(Master!$C$2:$C$918,"06. Binary Search",Master!$G$2:$G$918,"Core",Master!$J$2:$J$918,"Mastered")+COUNTIFS(Master!$C$2:$C$918,"07. Strings",Master!$G$2:$G$918,"Core",Master!$J$2:$J$918,"Solved")+COUNTIFS(Master!$C$2:$C$918,"07. Strings",Master!$G$2:$G$918,"Core",Master!$J$2:$J$918,"Mastered")+COUNTIFS(Master!$C$2:$C$918,"08. Hashing",Master!$G$2:$G$918,"Core",Master!$J$2:$J$918,"Solved")+COUNTIFS(Master!$C$2:$C$918,"08. Hashing",Master!$G$2:$G$918,"Core",Master!$J$2:$J$918,"Mastered")+COUNTIFS(Master!$C$2:$C$918,"09. Matrix / 2D",Master!$G$2:$G$918,"Core",Master!$J$2:$J$918,"Solved")+COUNTIFS(Master!$C$2:$C$918,"09. Matrix / 2D",Master!$G$2:$G$918,"Core",Master!$J$2:$J$918,"Mastered") | I10: =IFERROR($H10/$D10,0)
B11: Phase 3 - Linear DS | C11: 10 - 12: Linked List, Stack & Queue, Heap & Priority Queue | D11: =COUNTIFS(Master!$C$2:$C$918,"10. Linked List",Master!$G$2:$G$918,"Core")+COUNTIFS(Master!$C$2:$C$918,"11. Stack & Queue",Master!$G$2:$G$918,"Core")+COUNTIFS(Master!$C$2:$C$918,"12. Heap & Priority Queue",Master!$G$2:$G$918,"Core") | E11: =$E10+$D11 | F11: =ROUNDUP($E11/$C$6,0) | G11: =$C$5+$F11 | H11: =COUNTIFS(Master!$C$2:$C$918,"10. Linked List",Master!$G$2:$G$918,"Core",Master!$J$2:$J$918,"Solved")+COUNTIFS(Master!$C$2:$C$918,"10. Linked List",Master!$G$2:$G$918,"Core",Master!$J$2:$J$918,"Mastered")+COUNTIFS(Master!$C$2:$C$918,"11. Stack & Queue",Master!$G$2:$G$918,"Core",Master!$J$2:$J$918,"Solved")+COUNTIFS(Master!$C$2:$C$918,"11. Stack & Queue",Master!$G$2:$G$918,"Core",Master!$J$2:$J$918,"Mastered")+COUNTIFS(Master!$C$2:$C$918,"12. Heap & Priority Queue",Master!$G$2:$G$918,"Core",Master!$J$2:$J$918,"Solved")+COUNTIFS(Master!$C$2:$C$918,"12. Heap & Priority Queue",Master!$G$2:$G$918,"Core",Master!$J$2:$J$918,"Mastered") | I11: =IFERROR($H11/$D11,0)
B12: Phase 4 - Greedy & Backtracking | C12: 13 - 14: Greedy, Backtracking | D12: =COUNTIFS(Master!$C$2:$C$918,"13. Greedy",Master!$G$2:$G$918,"Core")+COUNTIFS(Master!$C$2:$C$918,"14. Backtracking",Master!$G$2:$G$918,"Core") | E12: =$E11+$D12 | F12: =ROUNDUP($E12/$C$6,0) | G12: =$C$5+$F12 | H12: =COUNTIFS(Master!$C$2:$C$918,"13. Greedy",Master!$G$2:$G$918,"Core",Master!$J$2:$J$918,"Solved")+COUNTIFS(Master!$C$2:$C$918,"13. Greedy",Master!$G$2:$G$918,"Core",Master!$J$2:$J$918,"Mastered")+COUNTIFS(Master!$C$2:$C$918,"14. Backtracking",Master!$G$2:$G$918,"Core",Master!$J$2:$J$918,"Solved")+COUNTIFS(Master!$C$2:$C$918,"14. Backtracking",Master!$G$2:$G$918,"Core",Master!$J$2:$J$918,"Mastered") | I12: =IFERROR($H12/$D12,0)
B13: Phase 5 - Trees & Graphs | C13: 15 - 17: Trees & BST, Tries, Graphs | D13: =COUNTIFS(Master!$C$2:$C$918,"15. Trees & BST",Master!$G$2:$G$918,"Core")+COUNTIFS(Master!$C$2:$C$918,"16. Tries",Master!$G$2:$G$918,"Core")+COUNTIFS(Master!$C$2:$C$918,"17. Graphs",Master!$G$2:$G$918,"Core") | E13: =$E12+$D13 | F13: =ROUNDUP($E13/$C$6,0) | G13: =$C$5+$F13 | H13: =COUNTIFS(Master!$C$2:$C$918,"15. Trees & BST",Master!$G$2:$G$918,"Core",Master!$J$2:$J$918,"Solved")+COUNTIFS(Master!$C$2:$C$918,"15. Trees & BST",Master!$G$2:$G$918,"Core",Master!$J$2:$J$918,"Mastered")+COUNTIFS(Master!$C$2:$C$918,"16. Tries",Master!$G$2:$G$918,"Core",Master!$J$2:$J$918,"Solved")+COUNTIFS(Master!$C$2:$C$918,"16. Tries",Master!$G$2:$G$918,"Core",Master!$J$2:$J$918,"Mastered")+COUNTIFS(Master!$C$2:$C$918,"17. Graphs",Master!$G$2:$G$918,"Core",Master!$J$2:$J$918,"Solved")+COUNTIFS(Master!$C$2:$C$918,"17. Graphs",Master!$G$2:$G$918,"Core",Master!$J$2:$J$918,"Mastered") | I13: =IFERROR($H13/$D13,0)
B14: Phase 6 - DP & Closers | C14: 18 - 23: Dynamic Programming, Bit Manipulation, Math & Number Theory, Intervals, Design, Advanced DS | D14: =COUNTIFS(Master!$C$2:$C$918,"18. Dynamic Programming",Master!$G$2:$G$918,"Core")+COUNTIFS(Master!$C$2:$C$918,"19. Bit Manipulation",Master!$G$2:$G$918,"Core")+COUNTIFS(Master!$C$2:$C$918,"20. Math & Number Theory",Master!$G$2:$G$918,"Core")+COUNTIFS(Master!$C$2:$C$918,"21. Intervals",Master!$G$2:$G$918,"Core")+COUNTIFS(Master!$C$2:$C$918,"22. Design",Master!$G$2:$G$918,"Core")+COUNTIFS(Master!$C$2:$C$918,"23. Advanced DS",Master!$G$2:$G$918,"Core") | E14: =$E13+$D14 | F14: =ROUNDUP($E14/$C$6,0) | G14: =$C$5+$F14 | H14: =COUNTIFS(Master!$C$2:$C$918,"18. Dynamic Programming",Master!$G$2:$G$918,"Core",Master!$J$2:$J$918,"Solved")+COUNTIFS(Master!$C$2:$C$918,"18. Dynamic Programming",Master!$G$2:$G$918,"Core",Master!$J$2:$J$918,"Mastered")+COUNTIFS(Master!$C$2:$C$918,"19. Bit Manipulation",Master!$G$2:$G$918,"Core",Master!$J$2:$J$918,"Solved")+COUNTIFS(Master!$C$2:$C$918,"19. Bit Manipulation",Master!$G$2:$G$918,"Core",Master!$J$2:$J$918,"Mastered")+COUNTIFS(Master!$C$2:$C$918,"20. Math & Number Theory",Master!$G$2:$G$918,"Core",Master!$J$2:$J$918,"Solved")+COUNTIFS(Master!$C$2:$C$918,"20. Math & Number Theory",Master!$G$2:$G$918,"Core",Master!$J$2:$J$918,"Mastered")+COUNTIFS(Master!$C$2:$C$918,"21. Intervals",Master!$G$2:$G$918,"Core",Master!$J$2:$J$918,"Solved")+COUNTIFS(Master!$C$2:$C$918,"21. Intervals",Master!$G$2:$G$918,"Core",Master!$J$2:$J$918,"Mastered")+COUNTIFS(Master!$C$2:$C$918,"22. Design",Master!$G$2:$G$918,"Core",Master!$J$2:$J$918,"Solved")+COUNTIFS(Master!$C$2:$C$918,"22. Design",Master!$G$2:$G$918,"Core",Master!$J$2:$J$918,"Mastered")+COUNTIFS(Master!$C$2:$C$918,"23. Advanced DS",Master!$G$2:$G$918,"Core",Master!$J$2:$J$918,"Solved")+COUNTIFS(Master!$C$2:$C$918,"23. Advanced DS",Master!$G$2:$G$918,"Core",Master!$J$2:$J$918,"Mastered") | I14: =IFERROR($H14/$D14,0)
B15: TOTAL | D15: =SUM(D9:D14) | G15: =$G14 | H15: =SUM(H9:H14) | I15: =IFERROR($H15/$D15,0)
B17: Reality check
B18: - Days assume you solve every single day. You will not. Multiply the total by about 1.4 for a number you can trust.
B19: - Depth problems are for after the Core track is done, or for a topic you are actively interviewing on.
B20: - Stretch problems (Hard + Advanced DS) are not placement-critical. Ignore them until the Core track is above 80%.
B21: - If a phase slips by more than two weeks, cut Depth entirely rather than moving the target date again.

Sheet Master
A1: Step | B1: Stage | C1: Topic | D1: Pattern | E1: Problem | F1: Difficulty | G1: Tier | H1: Platform | I1: Link | J1: Status | K1: Confidence | L1: Attempts | M1: Last Revised | N1: Next Revision | O1: Due? | P1: Notes
A2: 1 | B2: 1. Foundations - Core | C2: 01. Basics & Recursion | D2: Recursion warm-up | E2: Print 1 to N using Recursion | F2: Easy | G2: Core | H2: GeeksforGeeks | I2: https://www.geeksforgeeks.org/problems/print-1-to-n-without-using-loops3621/1 | J2: Not Started | N2: =IF($M2="","",$M2+IF($K2="",Dashboard!$M$9,INDEX(Dashboard!$M$5:$M$9,$K2))) | O2: =IF(OR($J2="Attempted",$J2="Revisit"),"DUE",IF($N2="","",IF($N2<=TODAY(),"DUE","")))
A3: 2 | B3: 1. Foundations - Core | C3: 01. Basics & Recursion | D3: Recursion warm-up | E3: Sum of First N Natural Numbers | F3: Easy | G3: Core | H3: GeeksforGeeks | I3: https://www.geeksforgeeks.org/problems/reverse-coding2452/1 | J3: Not Started | N3: =IF($M3="","",$M3+IF($K3="",Dashboard!$M$9,INDEX(Dashboard!$M$5:$M$9,$K3))) | O3: =IF(OR($J3="Attempted",$J3="Revisit"),"DUE",IF($N3="","",IF($N3<=TODAY(),"DUE","")))
A4: 3 | B4: 1. Foundations - Core | C4: 01. Basics & Recursion | D4: Recursion warm-up | E4: Factorial of a Number | F4: Easy | G4: Core | H4: GeeksforGeeks | I4: https://www.geeksforgeeks.org/problems/factorial5739/1 | J4: Not Started | N4: =IF($M4="","",$M4+IF($K4="",Dashboard!$M$9,INDEX(Dashboard!$M$5:$M$9,$K4))) | O4: =IF(OR($J4="Attempted",$J4="Revisit"),"DUE",IF($N4="","",IF($N4<=TODAY(),"DUE","")))
A5: 4 | B5: 1. Foundations - Core | C5: 01. Basics & Recursion | D5: Recursion warm-up | E5: Sum of Digits | F5: Easy | G5: Core | H5: GeeksforGeeks | I5: https://www.geeksforgeeks.org/problems/sum-of-digits1742/1 | J5: Not Started | N5: =IF($M5="","",$M5+IF($K5="",Dashboard!$M$9,INDEX(Dashboard!$M$5:$M$9,$K5))) | O5: =IF(OR($J5="Attempted",$J5="Revisit"),"DUE",IF($N5="","",IF($N5<=TODAY(),"DUE","")))
A6: 5 | B6: 1. Foundations - Core | C6: 01. Basics & Recursion | D6: Recursion warm-up | E6: Reverse an Array using Recursion | F6: Easy | G6: Core | H6: GeeksforGeeks | I6: https://www.geeksforgeeks.org/problems/reverse-an-array/1 | J6: Not Started | N6: =IF($M6="","",$M6+IF($K6="",Dashboard!$M$9,INDEX(Dashboard!$M$5:$M$9,$K6))) | O6: =IF(OR($J6="Attempted",$J6="Revisit"),"DUE",IF($N6="","",IF($N6<=TODAY(),"DUE","")))
A7: 6 | B7: 1. Foundations - Core | C7: 01. Basics & Recursion | D7: Recursion warm-up | E7: Palindrome String (recursive) | F7: Easy | G7: Core | H7: GeeksforGeeks | I7: https://www.geeksforgeeks.org/problems/palindrome-string0817/1 | J7: Not Started | N7: =IF($M7="","",$M7+IF($K7="",Dashboard!$M$9,INDEX(Dashboard!$M$5:$M$9,$K7))) | O7: =IF(OR($J7="Attempted",$J7="Revisit"),"DUE",IF($N7="","",IF($N7<=TODAY(),"DUE","")))
A8: 7 | B8: 1. Foundations - Core | C8: 01. Basics & Recursion | D8: Recursion warm-up | E8: Check if an Array is Sorted | F8: Easy | G8: Core | H8: GeeksforGeeks | I8: https://www.geeksforgeeks.org/problems/check-if-an-array-is-sorted0701/1 | J8: Not Started | N8: =IF($M8="","",$M8+IF($K8="",Dashboard!$M$9,INDEX(Dashboard!$M$5:$M$9,$K8))) | O8: =IF(OR($J8="Attempted",$J8="Revisit"),"DUE",IF($N8="","",IF($N8<=TODAY(),"DUE","")))
A9: 8 | B9: 1. Foundations - Core | C9: 01. Basics & Recursion | D9: Recursion warm-up | E9: Remove All Occurrences of a Character | F9: Easy | G9: Core | H9: GeeksforGeeks | I9: https://www.geeksforgeeks.org/problems/remove-all-occurrences-of-a-character-in-a-string/1 | J9: Not Started | N9: =IF($M9="","",$M9+IF($K9="",Dashboard!$M$9,INDEX(Dashboard!$M$5:$M$9,$K9))) | O9: =IF(OR($J9="Attempted",$J9="Revisit"),"DUE",IF($N9="","",IF($N9<=TODAY(),"DUE","")))
A10: 9 | B10: 1. Foundations - Core | C10: 01. Basics & Recursion | D10: Recursion warm-up | E10: Fibonacci Number | F10: Easy | G10: Core | H10: LeetCode | I10: https://leetcode.com/problems/fibonacci-number/ | J10: Not Started | N10: =IF($M10="","",$M10+IF($K10="",Dashboard!$M$9,INDEX(Dashboard!$M$5:$M$9,$K10))) | O10: =IF(OR($J10="Attempted",$J10="Revisit"),"DUE",IF($N10="","",IF($N10<=TODAY(),"DUE","")))
A11: 10 | B11: 1. Foundations - Core | C11: 01. Basics & Recursion | D11: Recursion warm-up | E11: Pow(x, n) | F11: Medium | G11: Core | H11: LeetCode | I11: https://leetcode.com/problems/powx-n/ | J11: Not Started | N11: =IF($M11="","",$M11+IF($K11="",Dashboard!$M$9,INDEX(Dashboard!$M$5:$M$9,$K11))) | O11: =IF(OR($J11="Attempted",$J11="Revisit"),"DUE",IF($N11="","",IF($N11<=TODAY(),"DUE","")))
A12: 11 | B12: 1. Foundations - Core | C12: 01. Basics & Recursion | D12: Divide & Conquer | E12: Merge Sort | F12: Medium | G12: Core | H12: GeeksforGeeks | I12: https://www.geeksforgeeks.org/problems/merge-sort/1 | J12: Not Started | N12: =IF($M12="","",$M12+IF($K12="",Dashboard!$M$9,INDEX(Dashboard!$M$5:$M$9,$K12))) | O12: =IF(OR($J12="Attempted",$J12="Revisit"),"DUE",IF($N12="","",IF($N12<=TODAY(),"DUE","")))
A13: 12 | B13: 1. Foundations - Core | C13: 01. Basics & Recursion | D13: Divide & Conquer | E13: Quick Sort | F13: Medium | G13: Core | H13: GeeksforGeeks | I13: https://www.geeksforgeeks.org/problems/quick-sort/1 | J13: Not Started | N13: =IF($M13="","",$M13+IF($K13="",Dashboard!$M$9,INDEX(Dashboard!$M$5:$M$9,$K13))) | O13: =IF(OR($J13="Attempted",$J13="Revisit"),"DUE",IF($N13="","",IF($N13<=TODAY(),"DUE","")))
... A18: 17 | B18: 1. Foundations - Core | C18: 02. Arrays & Two Pointers | D18: Basics | E18: Third Maximum Number | F18: Easy | G18: Core | H18: LeetCode | I18: https://leetcode.com/problems/third-maximum-number/ | J18: Not Started | N18: =IF($M18="","",$M18+IF($K18="",Dashboard!$M$9,INDEX(Dashboard!$M$5:$M$9,$K18))) | O18: =IF(OR($J18="Attempted",$J18="Revisit"),"DUE",IF($N18="","",IF($N18<=TODAY(),"DUE","")))
A19: 18 | B19: 1. Foundations - Core | C19: 02. Arrays & Two Pointers | D19: Two pointers | E19: Remove Duplicates from Sorted Array | F19: Easy | G19: Core | H19: LeetCode | I19: https://leetcode.com/problems/remove-duplicates-from-sorted-array/ | J19: Not Started | N19: =IF($M19="","",$M19+IF($K19="",Dashboard!$M$9,INDEX(Dashboard!$M$5:$M$9,$K19))) | O19: =IF(OR($J19="Attempted",$J19="Revisit"),"DUE",IF($N19="","",IF($N19<=TODAY(),"DUE",""))) | P19: v3 addition
A20: 19 | B20: 1. Foundations - Core | C20: 02. Arrays & Two Pointers | D20: Two pointers | E20: Move Zeroes | F20: Easy | G20: Core | H20: LeetCode | I20: https://leetcode.com/problems/move-zeroes/ | J20: Not Started | N20: =IF($M20="","",$M20+IF($K20="",Dashboard!$M$9,INDEX(Dashboard!$M$5:$M$9,$K20))) | O20: =IF(OR($J20="Attempted",$J20="Revisit"),"DUE",IF($N20="","",IF($N20<=TODAY(),"DUE",""))) | P20: v3 addition
A21: 20 | B21: 1. Foundations - Core | C21: 02. Arrays & Two Pointers | D21: Two pointers | E21: Sort Array By Parity | F21: Easy | G21: Core | H21: LeetCode | I21: https://leetcode.com/problems/sort-array-by-parity/ | J21: Not Started | N21: =IF($M21="","",$M21+IF($K21="",Dashboard!$M$9,INDEX(Dashboard!$M$5:$M$9,$K21))) | O21: =IF(OR($J21="Attempted",$J21="Revisit"),"DUE",IF($N21="","",IF($N21<=TODAY(),"DUE",""))) | P21: v3 addition
A22: 21 | B22: 1. Foundations - Core | C22: 02. Arrays & Two Pointers | D22: Two pointers | E22: Two Sum II - Input Array Is Sorted | F22: Medium | G22: Core | H22: LeetCode | I22: https://leetcode.com/problems/two-sum-ii-input-array-is-sorted/ | J22: Not Started | N22: =IF($M22="","",$M22+IF($K22="",Dashboard!$M$9,INDEX(Dashboard!$M$5:$M$9,$K22))) | O22: =IF(OR($J22="Attempted",$J22="Revisit"),"DUE",IF($N22="","",IF($N22<=TODAY(),"DUE","")))
A23: 22 | B23: 1. Foundations - Core | C23: 02. Arrays & Two Pointers | D23: Dutch National Flag | E23: Segregate 0s and 1s | F23: Easy | G23: Core | H23: GeeksforGeeks | I23: https://www.geeksforgeeks.org/problems/segregate-0s-and-1s5106/1 | J23: Not Started | N23: =IF($M23="","",$M23+IF($K23="",Dashboard!$M$9,INDEX(Dashboard!$M$5:$M$9,$K23))) | O23: =IF(OR($J23="Attempted",$J23="Revisit"),"DUE",IF($N23="","",IF($N23<=TODAY(),"DUE","")))
A24: 23 | B24: 1. Foundations - Core | C24: 02. Arrays & Two Pointers | D24: Dutch National Flag | E24: Sort Colors | F24: Medium | G24: Core | H24: LeetCode | I24: https://leetcode.com/problems/sort-colors/ | J24: Not Started | N24: =IF($M24="","",$M24+IF($K24="",Dashboard!$M$9,INDEX(Dashboard!$M$5:$M$9,$K24))) | O24: =IF(OR($J24="Attempted",$J24="Revisit"),"DUE",IF($N24="","",IF($N24<=TODAY(),"DUE","")))
A25: 24 | B25: 1. Foundations - Core | C25: 02. Arrays & Two Pointers | D25: Frequency scan | E25: Element Appearing More Than 25% In Sorted Array | F25: Easy | G25: Core | H25: LeetCode | I25: https://leetcode.com/problems/element-appearing-more-than-25-in-sorted-array/ | J25: Not Started | N25: =IF($M25="","",$M25+IF($K25="",Dashboard!$M$9,INDEX(Dashboard!$M$5:$M$9,$K25))) | O25: =IF(OR($J25="Attempted",$J25="Revisit"),"DUE",IF($N25="","",IF($N25<=TODAY(),"DUE",""))) | P25: v3 addition
A26: 25 | B26: 1. Foundations - Core | C26: 02. Arrays & Two Pointers | D26: Frequency scan | E26: Most Frequent Even Element | F26: Easy | G26: Core | H26: LeetCode | I26: https://leetcode.com/problems/most-frequent-even-element/ | J26: Not Started | N26: =IF($M26="","",$M26+IF($K26="",Dashboard!$M$9,INDEX(Dashboard!$M$5:$M$9,$K26))) | O26: =IF(OR($J26="Attempted",$J26="Revisit"),"DUE",IF($N26="","",IF($N26<=TODAY(),"DUE","")))
A27: 26 | B27: 1. Foundations - Core | C27: 02. Arrays & Two Pointers | D27: Voting / counting | E27: Majority Element | F27: Easy | G27: Core | H27: LeetCode | I27: https://leetcode.com/problems/majority-element/ | J27: Not Started | N27: =IF($M27="","",$M27+IF($K27="",Dashboard!$M$9,INDEX(Dashboard!$M$5:$M$9,$K27))) | O27: =IF(OR($J27="Attempted",$J27="Revisit"),"DUE",IF($N27="","",IF($N27<=TODAY(),"DUE",""))) | P27: v3 addition
A28: 27 | B28: 1. Foundations - Core | C28: 02. Arrays & Two Pointers | D28: Voting / counting | E28: Majority Element II | F28: Medium | G28: Core | H28: LeetCode | I28: https://leetcode.com/problems/majority-element-ii/ | J28: Not Started | N28: =IF($M28="","",$M28+IF($K28="",Dashboard!$M$9,INDEX(Dashboard!$M$5:$M$9,$K28))) | O28: =IF(OR($J28="Attempted",$J28="Revisit"),"DUE",IF($N28="","",IF($N28<=TODAY(),"DUE",""))) | P28: v3 addition
A29: 28 | B29: 1. Foundations - Core | C29: 02. Arrays & Two Pointers | D29: Rearrangement | E29: Rotate Array | F29: Medium | G29: Core | H29: LeetCode | I29: https://leetcode.com/problems/rotate-array/ | J29: Not Started | N29: =IF($M29="","",$M29+IF($K29="",Dashboard!$M$9,INDEX(Dashboard!$M$5:$M$9,$K29))) | O29: =IF(OR($J29="Attempted",$J29="Revisit"),"DUE",IF($N29="","",IF($N29<=TODAY(),"DUE",""))) | P29: v3 addition
A30: 29 | B30: 1. Foundations - Core | C30: 02. Arrays & Two Pointers | D30: Rearrangement | E30: Next Permutation | F30: Medium | G30: Core | H30: LeetCode | I30: https://leetcode.com/problems/next-permutation/ | J30: Not Started | N30: =IF($M30="","",$M30+IF($K30="",Dashboard!$M$9,INDEX(Dashboard!$M$5:$M$9,$K30))) | O30: =IF(OR($J30="Attempted",$J30="Revisit"),"DUE",IF($N30="","",IF($N30<=TODAY(),"DUE","")))
A31: 30 | B31: 1. Foundations - Core | C31: 02. Arrays & Two Pointers | D31: K-Sum | E31: Number of Arithmetic Triplets | F31: Easy | G31: Core | H31: LeetCode | I31: https://leetcode.com/problems/number-of-arithmetic-triplets/ | J31: Not Started | N31: =IF($M31="","",$M31+IF($K31="",Dashboard!$M$9,INDEX(Dashboard!$M$5:$M$9,$K31))) | O31: =IF(OR($J31="Attempted",$J31="Revisit"),"DUE",IF($N31="","",IF($N31<=TODAY(),"DUE","")))
A32: 31 | B32: 1. Foundations - Core | C32: 02. Arrays & Two Pointers | D32: K-Sum | E32: 3Sum | F32: Medium | G32: Core | H32: LeetCode | I32: https://leetcode.com/problems/3sum/ | J32: Not Started | N32: =IF($M32="","",$M32+IF($K32="",Dashboard!$M$9,INDEX(Dashboard!$M$5:$M$9,$K32))) | O32: =IF(OR($J32="Attempted",$J32="Revisit"),"DUE",IF($N32="","",IF($N32<=TODAY(),"DUE","")))
A33: 32 | B33: 1. Foundations - Core | C33: 02. Arrays & Two Pointers | D33: K-Sum | E33: 3Sum Closest | F33: Medium | G33: Core | H33: LeetCode | I33: https://leetcode.com/problems/3sum-closest/ | J33: Not Started | N33: =IF($M33="","",$M33+IF($K33="",Dashboard!$M$9,INDEX(Dashboard!$M$5:$M$9,$K33))) | O33: =IF(OR($J33="Attempted",$J33="Revisit"),"DUE",IF($N33="","",IF($N33<=TODAY(),"DUE",""))) | P33: v3 addition
A34: 33 | B34: 1. Foundations - Core | C34: 03. Sorting & Cyclic Sort | D34: Custom comparator | E34: Relative Sort Array | F34: Easy | G34: Core | H34: LeetCode | I34: https://leetcode.com/problems/relative-sort-array/ | J34: Not Started | N34: =IF($M34="","",$M34+IF($K34="",Dashboard!$M$9,INDEX(Dashboard!$M$5:$M$9,$K34))) | O34: =IF(OR($J34="Attempted",$J34="Revisit"),"DUE",IF($N34="","",IF($N34<=TODAY(),"DUE","")))
A35: 34 | B35: 1. Foundations - Core | C35: 03. Sorting & Cyclic Sort | D35: Custom comparator | E35: Rank Transform of an Array | F35: Easy | G35: Core | H35: LeetCode | I35: https://leetcode.com/problems/rank-transform-of-an-array/ | J35: Not Started | N35: =IF($M35="","",$M35+IF($K35="",Dashboard!$M$9,INDEX(Dashboard!$M$5:$M$9,$K35))) | O35: =IF(OR($J35="Attempted",$J35="Revisit"),"DUE",IF($N35="","",IF($N35<=TODAY(),"DUE","")))
A36: 35 | B36: 1. Foundations - Core | C36: 03. Sorting & Cyclic Sort | D36: Custom comparator | E36: Largest Number | F36: Medium | G36: Core | H36: LeetCode | I36: https://leetcode.com/problems/largest-number/ | J36: Not Started | N36: =IF($M36="","",$M36+IF($K36="",Dashboard!$M$9,INDEX(Dashboard!$M$5:$M$9,$K36))) | O36: =IF(OR($J36="Attempted",$J36="Revisit"),"DUE",IF($N36="","",IF($N36<=TODAY(),"DUE","")))
A37: 36 | B37: 1. Foundations - Core | C37: 03. Sorting & Cyclic Sort | D37: Counting sort | E37: Sort an Array by Increasing Frequency | F37: Easy | G37: Core | H37: LeetCode | I37: https://leetcode.com/problems/sort-array-by-increasing-frequency/ | J37: Not Started | N37: =IF($M37="","",$M37+IF($K37="",Dashboard!$M$9,INDEX(Dashboard!$M$5:$M$9,$K37))) | O37: =IF(OR($J37="Attempted",$J37="Revisit"),"DUE",IF($N37="","",IF($N37<=TODAY(),"DUE","")))
A38: 37 | B38: 1. Foundations - Core | C38: 03. Sorting & Cyclic Sort | D38: Counting sort | E38: Height Checker | F38: Easy | G38: Core | H38: LeetCode | I38: https://leetcode.com/problems/height-checker/ | J38: Not Started | N38: =IF($M38="","",$M38+IF($K38="",Dashboard!$M$9,INDEX(Dashboard!$M$5:$M$9,$K38))) | O38: =IF(OR($J38="Attempted",$J38="Revisit"),"DUE",IF($N38="","",IF($N38<=TODAY(),"DUE",""))) | P38: v3 addition
A39: 38 | B39: 1. Foundations - Core | C39: 03. Sorting & Cyclic Sort | D39: Counting sort | E39: Sort Even and Odd Indices Independently | F39: Easy | G39: Core | H39: LeetCode | I39: https://leetcode.com/problems/sort-even-and-odd-indices-independently/ | J39: Not Started | N39: =IF($M39="","",$M39+IF($K39="",Dashboard!$M$9,INDEX(Dashboard!$M$5:$M$9,$K39))) | O39: =IF(OR($J39="Attempted",$J39="Revisit"),"DUE",IF($N39="","",IF($N39<=TODAY(),"DUE","")))
A40: 39 | B40: 1. Foundations - Core | C40: 03. Sorting & Cyclic Sort | D40: Counting sort | E40: Maximum Number of Balls in a Box | F40: Easy | G40: Core | H40: LeetCode | I40: https://leetcode.com/problems/maximum-number-of-balls-in-a-box/ | J40: Not Started | N40: =IF($M40="","",$M40+IF($K40="",Dashboard!$M$9,INDEX(Dashboard!$M$5:$M$9,$K40))) | O40: =IF(OR($J40="Attempted",$J40="Revisit"),"DUE",IF($N40="","",IF($N40<=TODAY(),"DUE","")))
A41: 40 | B41: 1. Foundations - Core | C41: 03. Sorting & Cyclic Sort | D41: Cyclic sort | E41: Missing Number | F41: Easy | G41: Core | H41: LeetCode | I41: https://leetcode.com/problems/missing-number/ | J41: Not Started | N41: =IF($M41="","",$M41+IF($K41="",Dashboard!$M$9,INDEX(Dashboard!$M$5:$M$9,$K41))) | O41: =IF(OR($J41="Attempted",$J41="Revisit"),"DUE",IF($N41="","",IF($N41<=TODAY(),"DUE","")))
A42: 41 | B42: 1. Foundations - Core | C42: 03. Sorting & Cyclic Sort | D42: Cyclic sort | E42: Find All Numbers Disappeared in an Array | F42: Easy | G42: Core | H42: LeetCode | I42: https://leetcode.com/problems/find-all-numbers-disappeared-in-an-array/ | J42: Not Started | N42: =IF($M42="","",$M42+IF($K42="",Dashboard!$M$9,INDEX(Dashboard!$M$5:$M$9,$K42))) | O42: =IF(OR($J42="Attempted",$J42="Revisit"),"DUE",IF($N42="","",IF($N42<=TODAY(),"DUE","")))
A43: 42 | B43: 1. Foundations - Core | C43: 03. Sorting & Cyclic Sort | D43: Sorting application | E43: Largest Perimeter Triangle | F43: Easy | G43: Core | H43: LeetCode | I43: https://leetcode.com/problems/largest-perimeter-triangle/ | J43: Not Started | N43: =IF($M43="","",$M43+IF($K43="",Dashboard!$M$9,INDEX(Dashboard!$M$5:$M$9,$K43))) | O43: =IF(OR($J43="Attempted",$J43="Revisit"),"DUE",IF($N43="","",IF($N43<=TODAY(),"DUE","")))
A44: 43 | B44: 1. Foundations - Core | C44: 03. Sorting & Cyclic Sort | D44: Sorting application | E44: Minimum Absolute Difference | F44: Easy | G44: Core | H44: LeetCode | I44: https://leetcode.com/problems/minimum-absolute-difference/ | J44: Not Started | N44: =IF($M44="","",$M44+IF($K44="",Dashboard!$M$9,INDEX(Dashboard!$M$5:$M$9,$K44))) | O44: =IF(OR($J44="Attempted",$J44="Revisit"),"DUE",IF($N44="","",IF($N44<=TODAY(),"DUE","")))
A45: 44 | B45: 1. Foundations - Core | C45: 03. Sorting & Cyclic Sort | D45: Sorting application | E45: H-Index | F45: Medium | G45: Core | H45: LeetCode | I45: https://leetcode.com/problems/h-index/ | J45: Not Started | N45: =IF($M45="","",$M45+IF($K45="",Dashboard!$M$9,INDEX(Dashboard!$M$5:$M$9,$K45))) | O45: =IF(OR($J45="Attempted",$J45="Revisit"),"DUE",IF($N45="","",IF($N45<=TODAY(),"DUE","")))
A46: 45 | B46: 1. Foundations - Core | C46: 03. Sorting & Cyclic Sort | D46: Sorting application | E46: Wiggle Sort | F46: Medium | G46: Core | H46: LeetCode | I46: https://leetcode.com/problems/wiggle-sort/ | J46: Not Started | N46: =IF($M46="","",$M46+IF($K46="",Dashboard!$M$9,INDEX(Dashboard!$M$5:$M$9,$K46))) | O46: =IF(OR($J46="Attempted",$J46="Revisit"),"DUE",IF($N46="","",IF($N46<=TODAY(),"DUE","")))
A47: 46 | B47: 1. Foundations - Core | C47: 04. Hashing | D47: Set basics | E47: Contains Duplicate | F47: Easy | G47: Core | H47: LeetCode | I47: https://leetcode.com/problems/contains-duplicate/ | J47: Not Started | N47: =IF($M47="","",$M47+IF($K47="",Dashboard!$M$9,INDEX(Dashboard!$M$5:$M$9,$K47))) | O47: =IF(OR($J47="Attempted",$J47="Revisit"),"DUE",IF($N47="","",IF($N47<=TODAY(),"DUE","")))
A48: 47 | B48: 1. Foundations - Core | C48: 04. Hashing | D48: Set basics | E48: Contains Duplicate II | F48: Easy | G48: Core | H48: LeetCode | I48: https://leetcode.com/problems/contains-duplicate-ii/ | J48: Not Started | N48: =IF($M48="","",$M48+IF($K48="",Dashboard!$M$9,INDEX(Dashboard!$M$5:$M$9,$K48))) | O48: =IF(OR($J48="Attempted",$J48="Revisit"),"DUE",IF($N48="","",IF($N48<=TODAY(),"DUE","")))
A49: 48 | B49: 1. Foundations - Core | C49: 04. Hashing | D49: Set basics | E49: Unique Number of Occurrences | F49: Easy | G49: Core | H49: LeetCode | I49: https://leetcode.com/problems/unique-number-of-occurrences/ | J49: Not Started | N49: =IF($M49="","",$M49+IF($K49="",Dashboard!$M$9,INDEX(Dashboard!$M$5:$M$9,$K49))) | O49: =IF(OR($J49="Attempted",$J49="Revisit"),"DUE",IF($N49="","",IF($N49<=TODAY(),"DUE","")))
A50: 49 | B50: 1. Foundations - Core | C50: 04. Hashing | D50: Set basics | E50: Check If N and Its Double Exist | F50: Easy | G50: Core | H50: LeetCode | I50: https://leetcode.com/problems/check-if-n-and-its-double-exist/ | J50: Not Started | N50: =IF($M50="","",$M50+IF($K50="",Dashboard!$M$9,INDEX(Dashboard!$M$5:$M$9,$K50))) | O50: =IF(OR($J50="Attempted",$J50="Revisit"),"DUE",IF($N50="","",IF($N50<=TODAY(),"DUE","")))
... A53: 52 | B53: 1. Foundations - Core | C53: 04. Hashing | D53: Frequency map | E53: Ransom Note | F53: Easy | G53: Core | H53: LeetCode | I53: https://leetcode.com/problems/ransom-note/ | J53: Not Started | N53: =IF($M53="","",$M53+IF($K53="",Dashboard!$M$9,INDEX(Dashboard!$M$5:$M$9,$K53))) | O53: =IF(OR($J53="Attempted",$J53="Revisit"),"DUE",IF($N53="","",IF($N53<=TODAY(),"DUE","")))
A54: 53 | B54: 1. Foundations - Core | C54: 04. Hashing | D54: Set + scan | E54: Distribute Candies | F54: Easy | G54: Core | H54: LeetCode | I54: https://leetcode.com/problems/distribute-candies/ | J54: Not Started | N54: =IF($M54="","",$M54+IF($K54="",Dashboard!$M$9,INDEX(Dashboard!$M$5:$M$9,$K54))) | O54: =IF(OR($J54="Attempted",$J54="Revisit"),"DUE",IF($N54="","",IF($N54<=TODAY(),"DUE",""))) | P54: v3 addition
A55: 54 | B55: 1. Foundations - Core | C55: 04. Hashing | D55: Set + scan | E55: Maximum Number of Pairs in Array | F55: Easy | G55: Core | H55: LeetCode | I55: https://leetcode.com/problems/maximum-number-of-pairs-in-array/ | J55: Not Started | N55: =IF($M55="","",$M55+IF($K55="",Dashboard!$M$9,INDEX(Dashboard!$M$5:$M$9,$K55))) | O55: =IF(OR($J55="Attempted",$J55="Revisit"),"DUE",IF($N55="","",IF($N55<=TODAY(),"DUE","")))
A56: 55 | B56: 1. Foundations - Core | C56: 04. Hashing | D56: Set + scan | E56: Longest Harmonious Subsequence | F56: Easy | G56: Core | H56: LeetCode | I56: https://leetcode.com/problems/longest-harmonious-subsequence/ | J56: Not Started | N56: =IF($M56="","",$M56+IF($K56="",Dashboard!$M$9,INDEX(Dashboard!$M$5:$M$9,$K56))) | O56: =IF(OR($J56="Attempted",$J56="Revisit"),"DUE",IF($N56="","",IF($N56<=TODAY(),"DUE","")))
A57: 56 | B57: 1. Foundations - Core | C57: 04. Hashing | D57: Set + scan | E57: Longest Consecutive Sequence | F57: Medium | G57: Core | H57: LeetCode | I57: https://leetcode.com/problems/longest-consecutive-sequence/ | J57: Not Started | N57: =IF($M57="","",$M57+IF($K57="",Dashboard!$M$9,INDEX(Dashboard!$M$5:$M$9,$K57))) | O57: =IF(OR($J57="Attempted",$J57="Revisit"),"DUE",IF($N57="","",IF($N57<=TODAY(),"DUE","")))
A58: 57 | B58: 1. Foundations - Core | C58: 04. Hashing | D58: Cycle detection | E58: Happy Number | F58: Easy | G58: Core | H58: LeetCode | I58: https://leetcode.com/problems/happy-number/ | J58: Not Started | N58: =IF($M58="","",$M58+IF($K58="",Dashboard!$M$9,INDEX(Dashboard!$M$5:$M$9,$K58))) | O58: =IF(OR($J58="Attempted",$J58="Revisit"),"DUE",IF($N58="","",IF($N58<=TODAY(),"DUE","")))
A59: 58 | B59: 1. Foundations - Core | C59: 04. Hashing | D59: Grid hashing | E59: Number of Equivalent Domino Pairs | F59: Easy | G59: Core | H59: LeetCode | I59: https://leetcode.com/problems/number-of-equivalent-domino-pairs/ | J59: Not Started | N59: =IF($M59="","",$M59+IF($K59="",Dashboard!$M$9,INDEX(Dashboard!$M$5:$M$9,$K59))) | O59: =IF(OR($J59="Attempted",$J59="Revisit"),"DUE",IF($N59="","",IF($N59<=TODAY(),"DUE","")))
A60: 59 | B60: 1. Foundations - Core | C60: 04. Hashing | D60: Grid hashing | E60: Check if Every Row and Column Contains All Numbers | F60: Easy | G60: Core | H60: LeetCode | I60: https://leetcode.com/problems/check-if-every-row-and-column-contains-all-numbers/ | J60: Not Started | N60: =IF($M60="","",$M60+IF($K60="",Dashboard!$M$9,INDEX(Dashboard!$M$5:$M$9,$K60))) | O60: =IF(OR($J60="Attempted",$J60="Revisit"),"DUE",IF($N60="","",IF($N60<=TODAY(),"DUE",""))) | P60: v3 addition
A61: 60 | B61: 1. Foundations - Core | C61: 04. Hashing | D61: Grid hashing | E61: Valid Sudoku | F61: Medium | G61: Core | H61: LeetCode | I61: https://leetcode.com/problems/valid-sudoku/ | J61: Not Started | N61: =IF($M61="","",$M61+IF($K61="",Dashboard!$M$9,INDEX(Dashboard!$M$5:$M$9,$K61))) | O61: =IF(OR($J61="Attempted",$J61="Revisit"),"DUE",IF($N61="","",IF($N61<=TODAY(),"DUE","")))
A62: 61 | B62: 1. Foundations - Core | C62: 04. Hashing | D62: Line hashing | E62: Check If It Is a Straight Line | F62: Easy | G62: Core | H62: LeetCode | I62: https://leetcode.com/problems/check-if-it-is-a-straight-line/ | J62: Not Started | N62: =IF($M62="","",$M62+IF($K62="",Dashboard!$M$9,INDEX(Dashboard!$M$5:$M$9,$K62))) | O62: =IF(OR($J62="Attempted",$J62="Revisit"),"DUE",IF($N62="","",IF($N62<=TODAY(),"DUE","")))
A63: 62 | B63: 1. Foundations - Core | C63: 04. Hashing | D63: Line hashing | E63: Brick Wall | F63: Medium | G63: Core | H63: LeetCode | I63: https://leetcode.com/problems/brick-wall/ | J63: Not Started | N63: =IF($M63="","",$M63+IF($K63="",Dashboard!$M$9,INDEX(Dashboard!$M$5:$M$9,$K63))) | O63: =IF(OR($J63="Attempted",$J63="Revisit"),"DUE",IF($N63="","",IF($N63<=TODAY(),"DUE",""))) | P63: v3 addition
A64: 63 | B64: 1. Foundations - Core | C64: 04. Hashing | D64: Meet in the middle | E64: 4Sum II | F64: Medium | G64: Core | H64: LeetCode | I64: https://leetcode.com/problems/4sum-ii/ | J64: Not Started | N64: =IF($M64="","",$M64+IF($K64="",Dashboard!$M$9,INDEX(Dashboard!$M$5:$M$9,$K64))) | O64: =IF(OR($J64="Attempted",$J64="Revisit"),"DUE",IF($N64="","",IF($N64<=TODAY(),"DUE",""))) | P64: v3 addition
A65: 64 | B65: 1. Foundations - Core | C65: 05. Prefix Sum & Kadane | D65: Prefix basics | E65: Running Sum of 1d Array | F65: Easy | G65: Core | H65: LeetCode | I65: https://leetcode.com/problems/running-sum-of-1d-array/ | J65: Not Started | N65: =IF($M65="","",$M65+IF($K65="",Dashboard!$M$9,INDEX(Dashboard!$M$5:$M$9,$K65))) | O65: =IF(OR($J65="Attempted",$J65="Revisit"),"DUE",IF($N65="","",IF($N65<=TODAY(),"DUE",""))) | P65: v3 addition
A66: 65 | B66: 1. Foundations - Core | C66: 05. Prefix Sum & Kadane | D66: Prefix basics | E66: Find Pivot Index | F66: Easy | G66: Core | H66: LeetCode | I66: https://leetcode.com/problems/find-pivot-index/ | J66: Not Started | N66: =IF($M66="","",$M66+IF($K66="",Dashboard!$M$9,INDEX(Dashboard!$M$5:$M$9,$K66))) | O66: =IF(OR($J66="Attempted",$J66="Revisit"),"DUE",IF($N66="","",IF($N66<=TODAY(),"DUE","")))
A67: 66 | B67: 1. Foundations - Core | C67: 05. Prefix Sum & Kadane | D67: Prefix basics | E67: Product of Array Except Self | F67: Medium | G67: Core | H67: LeetCode | I67: https://leetcode.com/problems/product-of-array-except-self/ | J67: Not Started | N67: =IF($M67="","",$M67+IF($K67="",Dashboard!$M$9,INDEX(Dashboard!$M$5:$M$9,$K67))) | O67: =IF(OR($J67="Attempted",$J67="Revisit"),"DUE",IF($N67="","",IF($N67<=TODAY(),"DUE","")))
A68: 67 | B68: 1. Foundations - Core | C68: 05. Prefix Sum & Kadane | D68: Kadane | E68: Maximum Subarray | F68: Medium | G68: Core | H68: LeetCode | I68: https://leetcode.com/problems/maximum-subarray/ | J68: Not Started | N68: =IF($M68="","",$M68+IF($K68="",Dashboard!$M$9,INDEX(Dashboard!$M$5:$M$9,$K68))) | O68: =IF(OR($J68="Attempted",$J68="Revisit"),"DUE",IF($N68="","",IF($N68<=TODAY(),"DUE",""))) | P68: v3 addition
A69: 68 | B69: 1. Foundations - Core | C69: 05. Prefix Sum & Kadane | D69: Kadane | E69: Best Time to Buy and Sell Stock | F69: Easy | G69: Core | H69: LeetCode | I69: https://leetcode.com/problems/best-time-to-buy-and-sell-stock/ | J69: Not Started | N69: =IF($M69="","",$M69+IF($K69="",Dashboard!$M$9,INDEX(Dashboard!$M$5:$M$9,$K69))) | O69: =IF(OR($J69="Attempted",$J69="Revisit"),"DUE",IF($N69="","",IF($N69<=TODAY(),"DUE",""))) | P69: v3 addition
A70: 69 | B70: 1. Foundations - Core | C70: 05. Prefix Sum & Kadane | D70: Kadane | E70: Smallest Sum Contiguous Subarray | F70: Easy | G70: Core | H70: GeeksforGeeks | I70: https://www.geeksforgeeks.org/problems/smallest-sum-contiguous-subarray/1 | J70: Not Started | N70: =IF($M70="","",$M70+IF($K70="",Dashboard!$M$9,INDEX(Dashboard!$M$5:$M$9,$K70))) | O70: =IF(OR($J70="Attempted",$J70="Revisit"),"DUE",IF($N70="","",IF($N70<=TODAY(),"DUE","")))
A71: 70 | B71: 1. Foundations - Core | C71: 05. Prefix Sum & Kadane | D71: Kadane | E71: Maximum Product Subarray | F71: Medium | G71: Core | H71: LeetCode | I71: https://leetcode.com/problems/maximum-product-subarray/ | J71: Not Started | N71: =IF($M71="","",$M71+IF($K71="",Dashboard!$M$9,INDEX(Dashboard!$M$5:$M$9,$K71))) | O71: =IF(OR($J71="Attempted",$J71="Revisit"),"DUE",IF($N71="","",IF($N71<=TODAY(),"DUE","")))
A72: 71 | B72: 1. Foundations - Core | C72: 05. Prefix Sum & Kadane | D72: Prefix + HashMap | E72: Subarray Sum Equals K | F72: Medium | G72: Core | H72: LeetCode | I72: https://leetcode.com/problems/subarray-sum-equals-k/ | J72: Not Started | N72: =IF($M72="","",$M72+IF($K72="",Dashboard!$M$9,INDEX(Dashboard!$M$5:$M$9,$K72))) | O72: =IF(OR($J72="Attempted",$J72="Revisit"),"DUE",IF($N72="","",IF($N72<=TODAY(),"DUE","")))
A73: 72 | B73: 1. Foundations - Core | C73: 05. Prefix Sum & Kadane | D73: Prefix + HashMap | E73: Subarray Sums Divisible by K | F73: Medium | G73: Core | H73: LeetCode | I73: https://leetcode.com/problems/subarray-sums-divisible-by-k/ | J73: Not Started | N73: =IF($M73="","",$M73+IF($K73="",Dashboard!$M$9,INDEX(Dashboard!$M$5:$M$9,$K73))) | O73: =IF(OR($J73="Attempted",$J73="Revisit"),"DUE",IF($N73="","",IF($N73<=TODAY(),"DUE","")))
A74: 73 | B74: 1. Foundations - Core | C74: 05. Prefix Sum & Kadane | D74: Difference array | E74: Maximum Population Year | F74: Easy | G74: Core | H74: LeetCode | I74: https://leetcode.com/problems/maximum-population-year/ | J74: Not Started | N74: =IF($M74="","",$M74+IF($K74="",Dashboard!$M$9,INDEX(Dashboard!$M$5:$M$9,$K74))) | O74: =IF(OR($J74="Attempted",$J74="Revisit"),"DUE",IF($N74="","",IF($N74<=TODAY(),"DUE","")))
A75: 74 | B75: 1. Foundations - Core | C75: 05. Prefix Sum & Kadane | D75: Difference array | E75: Corporate Flight Bookings | F75: Medium | G75: Core | H75: LeetCode | I75: https://leetcode.com/problems/corporate-flight-bookings/ | J75: Not Started | N75: =IF($M75="","",$M75+IF($K75="",Dashboard!$M$9,INDEX(Dashboard!$M$5:$M$9,$K75))) | O75: =IF(OR($J75="Attempted",$J75="Revisit"),"DUE",IF($N75="","",IF($N75<=TODAY(),"DUE","")))
A76: 75 | B76: 1. Foundations - Core | C76: 05. Prefix Sum & Kadane | D76: Difference array | E76: Car Pooling | F76: Medium | G76: Core | H76: LeetCode | I76: https://leetcode.com/problems/car-pooling/ | J76: Not Started | N76: =IF($M76="","",$M76+IF($K76="",Dashboard!$M$9,INDEX(Dashboard!$M$5:$M$9,$K76))) | O76: =IF(OR($J76="Attempted",$J76="Revisit"),"DUE",IF($N76="","",IF($N76<=TODAY(),"DUE","")))
A77: 76 | B77: 1. Foundations - Core | C77: 06. Sliding Window | D77: Fixed window | E77: Maximum Average Subarray I | F77: Easy | G77: Core | H77: LeetCode | I77: https://leetcode.com/problems/maximum-average-subarray-i/ | J77: Not Started | N77: =IF($M77="","",$M77+IF($K77="",Dashboard!$M$9,INDEX(Dashboard!$M$5:$M$9,$K77))) | O77: =IF(OR($J77="Attempted",$J77="Revisit"),"DUE",IF($N77="","",IF($N77<=TODAY(),"DUE","")))
A78: 77 | B78: 1. Foundations - Core | C78: 06. Sliding Window | D78: Fixed window | E78: Max Sum Subarray of Size K | F78: Easy | G78: Core | H78: GeeksforGeeks | I78: https://www.geeksforgeeks.org/problems/max-sum-subarray-of-size-k5313/1 | J78: Not Started | N78: =IF($M78="","",$M78+IF($K78="",Dashboard!$M$9,INDEX(Dashboard!$M$5:$M$9,$K78))) | O78: =IF(OR($J78="Attempted",$J78="Revisit"),"DUE",IF($N78="","",IF($N78<=TODAY(),"DUE","")))
A79: 78 | B79: 1. Foundations - Core | C79: 06. Sliding Window | D79: Fixed window | E79: Substrings of Size Three with Distinct Characters | F79: Easy | G79: Core | H79: LeetCode | I79: https://leetcode.com/problems/substrings-of-size-three-with-distinct-characters/ | J79: Not Started | N79: =IF($M79="","",$M79+IF($K79="",Dashboard!$M$9,INDEX(Dashboard!$M$5:$M$9,$K79))) | O79: =IF(OR($J79="Attempted",$J79="Revisit"),"DUE",IF($N79="","",IF($N79<=TODAY(),"DUE","")))
A80: 79 | B80: 1. Foundations - Core | C80: 06. Sliding Window | D80: Variable window | E80: Minimum Size Subarray Sum | F80: Medium | G80: Core | H80: LeetCode | I80: https://leetcode.com/problems/minimum-size-subarray-sum/ | J80: Not Started | N80: =IF($M80="","",$M80+IF($K80="",Dashboard!$M$9,INDEX(Dashboard!$M$5:$M$9,$K80))) | O80: =IF(OR($J80="Attempted",$J80="Revisit"),"DUE",IF($N80="","",IF($N80<=TODAY(),"DUE","")))
A81: 80 | B81: 1. Foundations - Core | C81: 06. Sliding Window | D81: Variable window | E81: Longest Substring Without Repeating Characters | F81: Medium | G81: Core | H81: LeetCode | I81: https://leetcode.com/problems/longest-substring-without-repeating-characters/ | J81: Not Started | N81: =IF($M81="","",$M81+IF($K81="",Dashboard!$M$9,INDEX(Dashboard!$M$5:$M$9,$K81))) | O81: =IF(OR($J81="Attempted",$J81="Revisit"),"DUE",IF($N81="","",IF($N81<=TODAY(),"DUE","")))
... A83: 82 | B83: 1. Foundations - Core | C83: 06. Sliding Window | D83: Variable window | E83: Max Consecutive Ones III | F83: Medium | G83: Core | H83: LeetCode | I83: https://leetcode.com/problems/max-consecutive-ones-iii/ | J83: Not Started | N83: =IF($M83="","",$M83+IF($K83="",Dashboard!$M$9,INDEX(Dashboard!$M$5:$M$9,$K83))) | O83: =IF(OR($J83="Attempted",$J83="Revisit"),"DUE",IF($N83="","",IF($N83<=TODAY(),"DUE","")))
A84: 83 | B84: 1. Foundations - Core | C84: 06. Sliding Window | D84: Anagram window | E84: Permutation in String | F84: Medium | G84: Core | H84: LeetCode | I84: https://leetcode.com/problems/permutation-in-string/ | J84: Not Started | N84: =IF($M84="","",$M84+IF($K84="",Dashboard!$M$9,INDEX(Dashboard!$M$5:$M$9,$K84))) | O84: =IF(OR($J84="Attempted",$J84="Revisit"),"DUE",IF($N84="","",IF($N84<=TODAY(),"DUE",""))) | P84: v3 addition
A85: 84 | B85: 1. Foundations - Core | C85: 06. Sliding Window | D85: Anagram window | E85: Find All Anagrams in a String | F85: Medium | G85: Core | H85: LeetCode | I85: https://leetcode.com/problems/find-all-anagrams-in-a-string/ | J85: Not Started | N85: =IF($M85="","",$M85+IF($K85="",Dashboard!$M$9,INDEX(Dashboard!$M$5:$M$9,$K85))) | O85: =IF(OR($J85="Attempted",$J85="Revisit"),"DUE",IF($N85="","",IF($N85<=TODAY(),"DUE",""))) | P85: v3 addition
A86: 85 | B86: 1. Foundations - Core | C86: 06. Sliding Window | D86: Count exactly-K trick | E86: Binary Subarrays With Sum | F86: Medium | G86: Core | H86: LeetCode | I86: https://leetcode.com/problems/binary-subarrays-with-sum/ | J86: Not Started | N86: =IF($M86="","",$M86+IF($K86="",Dashboard!$M$9,INDEX(Dashboard!$M$5:$M$9,$K86))) | O86: =IF(OR($J86="Attempted",$J86="Revisit"),"DUE",IF($N86="","",IF($N86<=TODAY(),"DUE",""))) | P86: v3 addition
A87: 86 | B87: 1. Foundations - Core | C87: 06. Sliding Window | D87: Count exactly-K trick | E87: Count Number of Nice Subarrays | F87: Medium | G87: Core | H87: LeetCode | I87: https://leetcode.com/problems/count-number-of-nice-subarrays/ | J87: Not Started | N87: =IF($M87="","",$M87+IF($K87="",Dashboard!$M$9,INDEX(Dashboard!$M$5:$M$9,$K87))) | O87: =IF(OR($J87="Attempted",$J87="Revisit"),"DUE",IF($N87="","",IF($N87<=TODAY(),"DUE","")))
A88: 87 | B88: 1. Foundations - Core | C88: 06. Sliding Window | D88: Hard window | E88: Minimum Window Substring | F88: Hard | G88: Core | H88: LeetCode | I88: https://leetcode.com/problems/minimum-window-substring/ | J88: Not Started | N88: =IF($M88="","",$M88+IF($K88="",Dashboard!$M$9,INDEX(Dashboard!$M$5:$M$9,$K88))) | O88: =IF(OR($J88="Attempted",$J88="Revisit"),"DUE",IF($N88="","",IF($N88<=TODAY(),"DUE","")))
A89: 88 | B89: 1. Foundations - Depth | C89: 02. Arrays & Two Pointers | D89: Two pointers | E89: Squares of a Sorted Array | F89: Easy | G89: Depth | H89: LeetCode | I89: https://leetcode.com/problems/squares-of-a-sorted-array/ | J89: Not Started | N89: =IF($M89="","",$M89+IF($K89="",Dashboard!$M$9,INDEX(Dashboard!$M$5:$M$9,$K89))) | O89: =IF(OR($J89="Attempted",$J89="Revisit"),"DUE",IF($N89="","",IF($N89<=TODAY(),"DUE",""))) | P89: v3 addition
A90: 89 | B90: 1. Foundations - Depth | C90: 02. Arrays & Two Pointers | D90: Two pointers | E90: Merge Sorted Array | F90: Easy | G90: Depth | H90: LeetCode | I90: https://leetcode.com/problems/merge-sorted-array/ | J90: Not Started | N90: =IF($M90="","",$M90+IF($K90="",Dashboard!$M$9,INDEX(Dashboard!$M$5:$M$9,$K90))) | O90: =IF(OR($J90="Attempted",$J90="Revisit"),"DUE",IF($N90="","",IF($N90<=TODAY(),"DUE","")))
A91: 90 | B91: 1. Foundations - Depth | C91: 02. Arrays & Two Pointers | D91: Two pointers | E91: Valid Palindrome | F91: Easy | G91: Depth | H91: LeetCode | I91: https://leetcode.com/problems/valid-palindrome/ | J91: Not Started | N91: =IF($M91="","",$M91+IF($K91="",Dashboard!$M$9,INDEX(Dashboard!$M$5:$M$9,$K91))) | O91: =IF(OR($J91="Attempted",$J91="Revisit"),"DUE",IF($N91="","",IF($N91<=TODAY(),"DUE","")))
A92: 91 | B92: 1. Foundations - Depth | C92: 02. Arrays & Two Pointers | D92: Two pointers | E92: Valid Palindrome II | F92: Easy | G92: Depth | H92: LeetCode | I92: https://leetcode.com/problems/valid-palindrome-ii/ | J92: Not Started | N92: =IF($M92="","",$M92+IF($K92="",Dashboard!$M$9,INDEX(Dashboard!$M$5:$M$9,$K92))) | O92: =IF(OR($J92="Attempted",$J92="Revisit"),"DUE",IF($N92="","",IF($N92<=TODAY(),"DUE","")))
A93: 92 | B93: 1. Foundations - Depth | C93: 02. Arrays & Two Pointers | D93: Two pointers | E93: Backspace String Compare | F93: Easy | G93: Depth | H93: LeetCode | I93: https://leetcode.com/problems/backspace-string-compare/ | J93: Not Started | N93: =IF($M93="","",$M93+IF($K93="",Dashboard!$M$9,INDEX(Dashboard!$M$5:$M$9,$K93))) | O93: =IF(OR($J93="Attempted",$J93="Revisit"),"DUE",IF($N93="","",IF($N93<=TODAY(),"DUE",""))) | P93: v3 addition
A94: 93 | B94: 1. Foundations - Depth | C94: 02. Arrays & Two Pointers | D94: Two pointers | E94: Remove Duplicates from Sorted Array II | F94: Medium | G94: Depth | H94: LeetCode | I94: https://leetcode.com/problems/remove-duplicates-from-sorted-array-ii/ | J94: Not Started | N94: =IF($M94="","",$M94+IF($K94="",Dashboard!$M$9,INDEX(Dashboard!$M$5:$M$9,$K94))) | O94: =IF(OR($J94="Attempted",$J94="Revisit"),"DUE",IF($N94="","",IF($N94<=TODAY(),"DUE","")))
A95: 94 | B95: 1. Foundations - Depth | C95: 02. Arrays & Two Pointers | D95: Two pointers | E95: Container With Most Water | F95: Medium | G95: Depth | H95: LeetCode | I95: https://leetcode.com/problems/container-with-most-water/ | J95: Not Started | N95: =IF($M95="","",$M95+IF($K95="",Dashboard!$M$9,INDEX(Dashboard!$M$5:$M$9,$K95))) | O95: =IF(OR($J95="Attempted",$J95="Revisit"),"DUE",IF($N95="","",IF($N95<=TODAY(),"DUE","")))
A96: 95 | B96: 1. Foundations - Depth | C96: 02. Arrays & Two Pointers | D96: Two pointers | E96: Subarray Product Less Than K | F96: Medium | G96: Depth | H96: LeetCode | I96: https://leetcode.com/problems/subarray-product-less-than-k/ | J96: Not Started | N96: =IF($M96="","",$M96+IF($K96="",Dashboard!$M$9,INDEX(Dashboard!$M$5:$M$9,$K96))) | O96: =IF(OR($J96="Attempted",$J96="Revisit"),"DUE",IF($N96="","",IF($N96<=TODAY(),"DUE","")))
A97: 96 | B97: 1. Foundations - Depth | C97: 02. Arrays & Two Pointers | D97: Two pointers | E97: Boats to Save People | F97: Medium | G97: Depth | H97: LeetCode | I97: https://leetcode.com/problems/boats-to-save-people/ | J97: Not Started | N97: =IF($M97="","",$M97+IF($K97="",Dashboard!$M$9,INDEX(Dashboard!$M$5:$M$9,$K97))) | O97: =IF(OR($J97="Attempted",$J97="Revisit"),"DUE",IF($N97="","",IF($N97<=TODAY(),"DUE","")))
A98: 97 | B98: 1. Foundations - Depth | C98: 02. Arrays & Two Pointers | D98: Two pointers | E98: Longest Mountain in Array | F98: Medium | G98: Depth | H98: LeetCode | I98: https://leetcode.com/problems/longest-mountain-in-array/ | J98: Not Started | N98: =IF($M98="","",$M98+IF($K98="",Dashboard!$M$9,INDEX(Dashboard!$M$5:$M$9,$K98))) | O98: =IF(OR($J98="Attempted",$J98="Revisit"),"DUE",IF($N98="","",IF($N98<=TODAY(),"DUE","")))
A99: 98 | B99: 1. Foundations - Depth | C99: 02. Arrays & Two Pointers | D99: Dutch National Flag | E99: Sort Array By Parity II | F99: Easy | G99: Depth | H99: LeetCode | I99: https://leetcode.com/problems/sort-array-by-parity-ii/ | J99: Not Started | N99: =IF($M99="","",$M99+IF($K99="",Dashboard!$M$9,INDEX(Dashboard!$M$5:$M$9,$K99))) | O99: =IF(OR($J99="Attempted",$J99="Revisit"),"DUE",IF($N99="","",IF($N99<=TODAY(),"DUE","")))
A100: 99 | B100: 1. Foundations - Depth | C100: 02. Arrays & Two Pointers | D100: Dutch National Flag | E100: Partition Array According to Given Pivot | F100: Medium | G100: Depth | H100: LeetCode | I100: https://leetcode.com/problems/partition-array-according-to-given-pivot/ | J100: Not Started | N100: =IF($M100="","",$M100+IF($K100="",Dashboard!$M$9,INDEX(Dashboard!$M$5:$M$9,$K100))) | O100: =IF(OR($J100="Attempted",$J100="Revisit"),"DUE",IF($N100="","",IF($N100<=TODAY(),"DUE",""))) | P100: v3 addition
A101: 100 | B101: 1. Foundations - Depth | C101: 02. Arrays & Two Pointers | D101: Rearrangement | E101: Rearrange Array Elements by Sign | F101: Medium | G101: Depth | H101: LeetCode | I101: https://leetcode.com/problems/rearrange-array-elements-by-sign/ | J101: Not Started | N101: =IF($M101="","",$M101+IF($K101="",Dashboard!$M$9,INDEX(Dashboard!$M$5:$M$9,$K101))) | O101: =IF(OR($J101="Attempted",$J101="Revisit"),"DUE",IF($N101="","",IF($N101<=TODAY(),"DUE",""))) | P101: v3 addition
A102: 101 | B102: 1. Foundations - Depth | C102: 02. Arrays & Two Pointers | D102: Rearrangement | E102: Shortest Unsorted Continuous Subarray | F102: Medium | G102: Depth | H102: LeetCode | I102: https://leetcode.com/problems/shortest-unsorted-continuous-subarray/ | J102: Not Started | N102: =IF($M102="","",$M102+IF($K102="",Dashboard!$M$9,INDEX(Dashboard!$M$5:$M$9,$K102))) | O102: =IF(OR($J102="Attempted",$J102="Revisit"),"DUE",IF($N102="","",IF($N102<=TODAY(),"DUE",""))) | P102: v3 addition
A103: 102 | B103: 1. Foundations - Depth | C103: 02. Arrays & Two Pointers | D103: Rearrangement | E103: Rearrange Array Alternately | F103: Medium | G103: Depth | H103: GeeksforGeeks | I103: https://www.geeksforgeeks.org/search/?q=Rearrange+Array+Alternately | J103: Not Started | N103: =IF($M103="","",$M103+IF($K103="",Dashboard!$M$9,INDEX(Dashboard!$M$5:$M$9,$K103))) | O103: =IF(OR($J103="Attempted",$J103="Revisit"),"DUE",IF($N103="","",IF($N103<=TODAY(),"DUE","")))
A104: 103 | B104: 1. Foundations - Depth | C104: 02. Arrays & Two Pointers | D104: K-Sum | E104: 4Sum | F104: Medium | G104: Depth | H104: LeetCode | I104: https://leetcode.com/problems/4sum/ | J104: Not Started | N104: =IF($M104="","",$M104+IF($K104="",Dashboard!$M$9,INDEX(Dashboard!$M$5:$M$9,$K104))) | O104: =IF(OR($J104="Attempted",$J104="Revisit"),"DUE",IF($N104="","",IF($N104<=TODAY(),"DUE",""))) | P104: v3 addition
A105: 104 | B105: 1. Foundations - Depth | C105: 02. Arrays & Two Pointers | D105: K-Sum | E105: Count Triplets with Sum Smaller than X | F105: Medium | G105: Depth | H105: GeeksforGeeks | I105: https://www.geeksforgeeks.org/problems/count-triplets-with-sum-smaller-than-x5549/1 | J105: Not Started | N105: =IF($M105="","",$M105+IF($K105="",Dashboard!$M$9,INDEX(Dashboard!$M$5:$M$9,$K105))) | O105: =IF(OR($J105="Attempted",$J105="Revisit"),"DUE",IF($N105="","",IF($N105<=TODAY(),"DUE",""))) | P105: v3 addition
A106: 105 | B106: 1. Foundations - Depth | C106: 02. Arrays & Two Pointers | D106: Index cycles | E106: Circular Array Loop | F106: Medium | G106: Depth | H106: LeetCode | I106: https://leetcode.com/problems/circular-array-loop/ | J106: Not Started | N106: =IF($M106="","",$M106+IF($K106="",Dashboard!$M$9,INDEX(Dashboard!$M$5:$M$9,$K106))) | O106: =IF(OR($J106="Attempted",$J106="Revisit"),"DUE",IF($N106="","",IF($N106<=TODAY(),"DUE",""))) | P106: v3 addition
A107: 106 | B107: 1. Foundations - Depth | C107: 02. Arrays & Two Pointers | D107: Index cycles | E107: Array Nesting | F107: Medium | G107: Depth | H107: LeetCode | I107: https://leetcode.com/problems/array-nesting/ | J107: Not Started | N107: =IF($M107="","",$M107+IF($K107="",Dashboard!$M$9,INDEX(Dashboard!$M$5:$M$9,$K107))) | O107: =IF(OR($J107="Attempted",$J107="Revisit"),"DUE",IF($N107="","",IF($N107<=TODAY(),"DUE",""))) | P107: v3 addition
...

Sheet Dashboard
B2: Progress Dashboard
B3: Every number here is calculated from the Master tab. Do not type into this sheet except the yellow config cells. | L3: CONFIG - revision gap (days)
L4: Confidence | M4: Days
B5: CORE TRACK (the one that matters) | C5: =COUNTIFS(Master!$G$2:$G$918,"Core",Master!$J$2:$J$918,"Solved")+COUNTIFS(Master!$G$2:$G$918,"Core",Master!$J$2:$J$918,"Mastered") | D5: =COUNTIF(Master!$G$2:$G$918,"Core") | E5: =IFERROR($C5/$D5,0) | L5: 1 | M5: 2
B6: All 922 questions | C6: =COUNTIF(Master!$J$2:$J$918,"Solved")+COUNTIF(Master!$J$2:$J$918,"Mastered") | D6: =COUNTA(Master!$A$2:$A$918) | E6: =IFERROR($C6/$D6,0) | L6: 2 | M6: 4
B7: Due for revision today | C7: =COUNTIF(Master!$O$2:$O$918,"DUE") | L7: 3 | M7: 7
L8: 4 | M8: 21
B9: Topic | C9: Total | D9: Core | E9: Done | F9: Core done | G9: Attempted | H9: Avg conf | I9: % Core done | L9: 5 | M9: 45
B10: 01. Basics & Recursion | C10: =COUNTIF(Master!$C$2:$C$918,$B10) | D10: =COUNTIFS(Master!$C$2:$C$918,$B10,Master!$G$2:$G$918,"Core") | E10: =COUNTIFS(Master!$C$2:$C$918,$B10,Master!$J$2:$J$918,"Solved")+COUNTIFS(Master!$C$2:$C$918,$B10,Master!$J$2:$J$918,"Mastered") | F10: =COUNTIFS(Master!$C$2:$C$918,$B10,Master!$G$2:$G$918,"Core",Master!$J$2:$J$918,"Solved")+COUNTIFS(Master!$C$2:$C$918,$B10,Master!$G$2:$G$918,"Core",Master!$J$2:$J$918,"Mastered") | G10: =COUNTIFS(Master!$C$2:$C$918,$B10,Master!$J$2:$J$918,"Attempted")+COUNTIFS(Master!$C$2:$C$918,$B10,Master!$J$2:$J$918,"Revisit") | H10: =IFERROR(AVERAGEIFS(Master!$K$2:$K$918,Master!$C$2:$C$918,$B10),"") | I10: =IFERROR($F10/$C10,0) | L10: Editable. Master!N uses these to set Next Revision.
B11: 02. Arrays & Two Pointers | C11: =COUNTIF(Master!$C$2:$C$918,$B11) | D11: =COUNTIFS(Master!$C$2:$C$918,$B11,Master!$G$2:$G$918,"Core") | E11: =COUNTIFS(Master!$C$2:$C$918,$B11,Master!$J$2:$J$918,"Solved")+COUNTIFS(Master!$C$2:$C$918,$B11,Master!$J$2:$J$918,"Mastered") | F11: =COUNTIFS(Master!$C$2:$C$918,$B11,Master!$G$2:$G$918,"Core",Master!$J$2:$J$918,"Solved")+COUNTIFS(Master!$C$2:$C$918,$B11,Master!$G$2:$G$918,"Core",Master!$J$2:$J$918,"Mastered") | G11: =COUNTIFS(Master!$C$2:$C$918,$B11,Master!$J$2:$J$918,"Attempted")+COUNTIFS(Master!$C$2:$C$918,$B11,Master!$J$2:$J$918,"Revisit") | H11: =IFERROR(AVERAGEIFS(Master!$K$2:$K$918,Master!$C$2:$C$918,$B11),"") | I11: =IFERROR($F11/$C11,0)
B12: 03. Sliding Window | C12: =COUNTIF(Master!$C$2:$C$918,$B12) | D12: =COUNTIFS(Master!$C$2:$C$918,$B12,Master!$G$2:$G$918,"Core") | E12: =COUNTIFS(Master!$C$2:$C$918,$B12,Master!$J$2:$J$918,"Solved")+COUNTIFS(Master!$C$2:$C$918,$B12,Master!$J$2:$J$918,"Mastered") | F12: =COUNTIFS(Master!$C$2:$C$918,$B12,Master!$G$2:$G$918,"Core",Master!$J$2:$J$918,"Solved")+COUNTIFS(Master!$C$2:$C$918,$B12,Master!$G$2:$G$918,"Core",Master!$J$2:$J$918,"Mastered") | G12: =COUNTIFS(Master!$C$2:$C$918,$B12,Master!$J$2:$J$918,"Attempted")+COUNTIFS(Master!$C$2:$C$918,$B12,Master!$J$2:$J$918,"Revisit") | H12: =IFERROR(AVERAGEIFS(Master!$K$2:$K$918,Master!$C$2:$C$918,$B12),"") | I12: =IFERROR($F12/$C12,0)
B13: 04. Prefix Sum & Kadane | C13: =COUNTIF(Master!$C$2:$C$918,$B13) | D13: =COUNTIFS(Master!$C$2:$C$918,$B13,Master!$G$2:$G$918,"Core") | E13: =COUNTIFS(Master!$C$2:$C$918,$B13,Master!$J$2:$J$918,"Solved")+COUNTIFS(Master!$C$2:$C$918,$B13,Master!$J$2:$J$918,"Mastered") | F13: =COUNTIFS(Master!$C$2:$C$918,$B13,Master!$G$2:$G$918,"Core",Master!$J$2:$J$918,"Solved")+COUNTIFS(Master!$C$2:$C$918,$B13,Master!$G$2:$G$918,"Core",Master!$J$2:$J$918,"Mastered") | G13: =COUNTIFS(Master!$C$2:$C$918,$B13,Master!$J$2:$J$918,"Attempted")+COUNTIFS(Master!$C$2:$C$918,$B13,Master!$J$2:$J$918,"Revisit") | H13: =IFERROR(AVERAGEIFS(Master!$K$2:$K$918,Master!$C$2:$C$918,$B13),"") | I13: =IFERROR($F13/$C13,0)
B14: 05. Sorting & Cyclic Sort | C14: =COUNTIF(Master!$C$2:$C$918,$B14) | D14: =COUNTIFS(Master!$C$2:$C$918,$B14,Master!$G$2:$G$918,"Core") | E14: =COUNTIFS(Master!$C$2:$C$918,$B14,Master!$J$2:$J$918,"Solved")+COUNTIFS(Master!$C$2:$C$918,$B14,Master!$J$2:$J$918,"Mastered") | F14: =COUNTIFS(Master!$C$2:$C$918,$B14,Master!$G$2:$G$918,"Core",Master!$J$2:$J$918,"Solved")+COUNTIFS(Master!$C$2:$C$918,$B14,Master!$G$2:$G$918,"Core",Master!$J$2:$J$918,"Mastered") | G14: =COUNTIFS(Master!$C$2:$C$918,$B14,Master!$J$2:$J$918,"Attempted")+COUNTIFS(Master!$C$2:$C$918,$B14,Master!$J$2:$J$918,"Revisit") | H14: =IFERROR(AVERAGEIFS(Master!$K$2:$K$918,Master!$C$2:$C$918,$B14),"") | I14: =IFERROR($F14/$C14,0)
B15: 06. Binary Search | C15: =COUNTIF(Master!$C$2:$C$918,$B15) | D15: =COUNTIFS(Master!$C$2:$C$918,$B15,Master!$G$2:$G$918,"Core") | E15: =COUNTIFS(Master!$C$2:$C$918,$B15,Master!$J$2:$J$918,"Solved")+COUNTIFS(Master!$C$2:$C$918,$B15,Master!$J$2:$J$918,"Mastered") | F15: =COUNTIFS(Master!$C$2:$C$918,$B15,Master!$G$2:$G$918,"Core",Master!$J$2:$J$918,"Solved")+COUNTIFS(Master!$C$2:$C$918,$B15,Master!$G$2:$G$918,"Core",Master!$J$2:$J$918,"Mastered") | G15: =COUNTIFS(Master!$C$2:$C$918,$B15,Master!$J$2:$J$918,"Attempted")+COUNTIFS(Master!$C$2:$C$918,$B15,Master!$J$2:$J$918,"Revisit") | H15: =IFERROR(AVERAGEIFS(Master!$K$2:$K$918,Master!$C$2:$C$918,$B15),"") | I15: =IFERROR($F15/$C15,0)
B16: 07. Strings | C16: =COUNTIF(Master!$C$2:$C$918,$B16) | D16: =COUNTIFS(Master!$C$2:$C$918,$B16,Master!$G$2:$G$918,"Core") | E16: =COUNTIFS(Master!$C$2:$C$918,$B16,Master!$J$2:$J$918,"Solved")+COUNTIFS(Master!$C$2:$C$918,$B16,Master!$J$2:$J$918,"Mastered") | F16: =COUNTIFS(Master!$C$2:$C$918,$B16,Master!$G$2:$G$918,"Core",Master!$J$2:$J$918,"Solved")+COUNTIFS(Master!$C$2:$C$918,$B16,Master!$G$2:$G$918,"Core",Master!$J$2:$J$918,"Mastered") | G16: =COUNTIFS(Master!$C$2:$C$918,$B16,Master!$J$2:$J$918,"Attempted")+COUNTIFS(Master!$C$2:$C$918,$B16,Master!$J$2:$J$918,"Revisit") | H16: =IFERROR(AVERAGEIFS(Master!$K$2:$K$918,Master!$C$2:$C$918,$B16),"") | I16: =IFERROR($F16/$C16,0)
B17: 08. Hashing | C17: =COUNTIF(Master!$C$2:$C$918,$B17) | D17: =COUNTIFS(Master!$C$2:$C$918,$B17,Master!$G$2:$G$918,"Core") | E17: =COUNTIFS(Master!$C$2:$C$918,$B17,Master!$J$2:$J$918,"Solved")+COUNTIFS(Master!$C$2:$C$918,$B17,Master!$J$2:$J$918,"Mastered") | F17: =COUNTIFS(Master!$C$2:$C$918,$B17,Master!$G$2:$G$918,"Core",Master!$J$2:$J$918,"Solved")+COUNTIFS(Master!$C$2:$C$918,$B17,Master!$G$2:$G$918,"Core",Master!$J$2:$J$918,"Mastered") | G17: =COUNTIFS(Master!$C$2:$C$918,$B17,Master!$J$2:$J$918,"Attempted")+COUNTIFS(Master!$C$2:$C$918,$B17,Master!$J$2:$J$918,"Revisit") | H17: =IFERROR(AVERAGEIFS(Master!$K$2:$K$918,Master!$C$2:$C$918,$B17),"") | I17: =IFERROR($F17/$C17,0)
B18: 09. Matrix / 2D | C18: =COUNTIF(Master!$C$2:$C$918,$B18) | D18: =COUNTIFS(Master!$C$2:$C$918,$B18,Master!$G$2:$G$918,"Core") | E18: =COUNTIFS(Master!$C$2:$C$918,$B18,Master!$J$2:$J$918,"Solved")+COUNTIFS(Master!$C$2:$C$918,$B18,Master!$J$2:$J$918,"Mastered") | F18: =COUNTIFS(Master!$C$2:$C$918,$B18,Master!$G$2:$G$918,"Core",Master!$J$2:$J$918,"Solved")+COUNTIFS(Master!$C$2:$C$918,$B18,Master!$G$2:$G$918,"Core",Master!$J$2:$J$918,"Mastered") | G18: =COUNTIFS(Master!$C$2:$C$918,$B18,Master!$J$2:$J$918,"Attempted")+COUNTIFS(Master!$C$2:$C$918,$B18,Master!$J$2:$J$918,"Revisit") | H18: =IFERROR(AVERAGEIFS(Master!$K$2:$K$918,Master!$C$2:$C$918,$B18),"") | I18: =IFERROR($F18/$C18,0)
B19: 10. Linked List | C19: =COUNTIF(Master!$C$2:$C$918,$B19) | D19: =COUNTIFS(Master!$C$2:$C$918,$B19,Master!$G$2:$G$918,"Core") | E19: =COUNTIFS(Master!$C$2:$C$918,$B19,Master!$J$2:$J$918,"Solved")+COUNTIFS(Master!$C$2:$C$918,$B19,Master!$J$2:$J$918,"Mastered") | F19: =COUNTIFS(Master!$C$2:$C$918,$B19,Master!$G$2:$G$918,"Core",Master!$J$2:$J$918,"Solved")+COUNTIFS(Master!$C$2:$C$918,$B19,Master!$G$2:$G$918,"Core",Master!$J$2:$J$918,"Mastered") | G19: =COUNTIFS(Master!$C$2:$C$918,$B19,Master!$J$2:$J$918,"Attempted")+COUNTIFS(Master!$C$2:$C$918,$B19,Master!$J$2:$J$918,"Revisit") | H19: =IFERROR(AVERAGEIFS(Master!$K$2:$K$918,Master!$C$2:$C$918,$B19),"") | I19: =IFERROR($F19/$C19,0)
B20: 11. Stack & Queue | C20: =COUNTIF(Master!$C$2:$C$918,$B20) | D20: =COUNTIFS(Master!$C$2:$C$918,$B20,Master!$G$2:$G$918,"Core") | E20: =COUNTIFS(Master!$C$2:$C$918,$B20,Master!$J$2:$J$918,"Solved")+COUNTIFS(Master!$C$2:$C$918,$B20,Master!$J$2:$J$918,"Mastered") | F20: =COUNTIFS(Master!$C$2:$C$918,$B20,Master!$G$2:$G$918,"Core",Master!$J$2:$J$918,"Solved")+COUNTIFS(Master!$C$2:$C$918,$B20,Master!$G$2:$G$918,"Core",Master!$J$2:$J$918,"Mastered") | G20: =COUNTIFS(Master!$C$2:$C$918,$B20,Master!$J$2:$J$918,"Attempted")+COUNTIFS(Master!$C$2:$C$918,$B20,Master!$J$2:$J$918,"Revisit") | H20: =IFERROR(AVERAGEIFS(Master!$K$2:$K$918,Master!$C$2:$C$918,$B20),"") | I20: =IFERROR($F20/$C20,0)
B21: 12. Heap & Priority Queue | C21: =COUNTIF(Master!$C$2:$C$918,$B21) | D21: =COUNTIFS(Master!$C$2:$C$918,$B21,Master!$G$2:$G$918,"Core") | E21: =COUNTIFS(Master!$C$2:$C$918,$B21,Master!$J$2:$J$918,"Solved")+COUNTIFS(Master!$C$2:$C$918,$B21,Master!$J$2:$J$918,"Mastered") | F21: =COUNTIFS(Master!$C$2:$C$918,$B21,Master!$G$2:$G$918,"Core",Master!$J$2:$J$918,"Solved")+COUNTIFS(Master!$C$2:$C$918,$B21,Master!$G$2:$G$918,"Core",Master!$J$2:$J$918,"Mastered") | G21: =COUNTIFS(Master!$C$2:$C$918,$B21,Master!$J$2:$J$918,"Attempted")+COUNTIFS(Master!$C$2:$C$918,$B21,Master!$J$2:$J$918,"Revisit") | H21: =IFERROR(AVERAGEIFS(Master!$K$2:$K$918,Master!$C$2:$C$918,$B21),"") | I21: =IFERROR($F21/$C21,0)
B22: 13. Greedy | C22: =COUNTIF(Master!$C$2:$C$918,$B22) | D22: =COUNTIFS(Master!$C$2:$C$918,$B22,Master!$G$2:$G$918,"Core") | E22: =COUNTIFS(Master!$C$2:$C$918,$B22,Master!$J$2:$J$918,"Solved")+COUNTIFS(Master!$C$2:$C$918,$B22,Master!$J$2:$J$918,"Mastered") | F22: =COUNTIFS(Master!$C$2:$C$918,$B22,Master!$G$2:$G$918,"Core",Master!$J$2:$J$918,"Solved")+COUNTIFS(Master!$C$2:$C$918,$B22,Master!$G$2:$G$918,"Core",Master!$J$2:$J$918,"Mastered") | G22: =COUNTIFS(Master!$C$2:$C$918,$B22,Master!$J$2:$J$918,"Attempted")+COUNTIFS(Master!$C$2:$C$918,$B22,Master!$J$2:$J$918,"Revisit") | H22: =IFERROR(AVERAGEIFS(Master!$K$2:$K$918,Master!$C$2:$C$918,$B22),"") | I22: =IFERROR($F22/$C22,0)
... B32: 23. Advanced DS | C32: =COUNTIF(Master!$C$2:$C$918,$B32) | D32: =COUNTIFS(Master!$C$2:$C$918,$B32,Master!$G$2:$G$918,"Core") | E32: =COUNTIFS(Master!$C$2:$C$918,$B32,Master!$J$2:$J$918,"Solved")+COUNTIFS(Master!$C$2:$C$918,$B32,Master!$J$2:$J$918,"Mastered") | F32: =COUNTIFS(Master!$C$2:$C$918,$B32,Master!$G$2:$G$918,"Core",Master!$J$2:$J$918,"Solved")+COUNTIFS(Master!$C$2:$C$918,$B32,Master!$G$2:$G$918,"Core",Master!$J$2:$J$918,"Mastered") | G32: =COUNTIFS(Master!$C$2:$C$918,$B32,Master!$J$2:$J$918,"Attempted")+COUNTIFS(Master!$C$2:$C$918,$B32,Master!$J$2:$J$918,"Revisit") | H32: =IFERROR(AVERAGEIFS(Master!$K$2:$K$918,Master!$C$2:$C$918,$B32),"") | I32: =IFERROR($F32/$C32,0)
B33: TOTAL | C33: =SUM(C10:C32) | D33: =SUM(D10:D32) | E33: =SUM(E10:E32) | F33: =SUM(F10:F32) | G33: =SUM(G10:G32) | H33: =IFERROR(AVERAGEIFS(Master!$K$2:$K$918,Master!$K$2:$K$918,">0"),"") | I33: =IFERROR($F33/$C33,0)
B35: By difficulty | G35: By status
C36: Total | D36: Done | E36: % | H36: Count
B37: Easy | C37: =COUNTIF(Master!$F$2:$F$918,$B37) | D37: =COUNTIFS(Master!$F$2:$F$918,$B37,Master!$J$2:$J$918,"Solved")+COUNTIFS(Master!$F$2:$F$918,$B37,Master!$J$2:$J$918,"Mastered") | E37: =IFERROR($D37/$C37,0) | G37: Not Started | H37: =COUNTIF(Master!$J$2:$J$918,$G37)
B38: Medium | C38: =COUNTIF(Master!$F$2:$F$918,$B38) | D38: =COUNTIFS(Master!$F$2:$F$918,$B38,Master!$J$2:$J$918,"Solved")+COUNTIFS(Master!$F$2:$F$918,$B38,Master!$J$2:$J$918,"Mastered") | E38: =IFERROR($D38/$C38,0) | G38: Attempted | H38: =COUNTIF(Master!$J$2:$J$918,$G38)
B39: Hard | C39: =COUNTIF(Master!$F$2:$F$918,$B39) | D39: =COUNTIFS(Master!$F$2:$F$918,$B39,Master!$J$2:$J$918,"Solved")+COUNTIFS(Master!$F$2:$F$918,$B39,Master!$J$2:$J$918,"Mastered") | E39: =IFERROR($D39/$C39,0) | G39: Solved | H39: =COUNTIF(Master!$J$2:$J$918,$G39)
G40: Mastered | H40: =COUNTIF(Master!$J$2:$J$918,$G40)
G41: Revisit | H41: =COUNTIF(Master!$J$2:$J$918,$G41)

Sheet Pattern Radar
B2: Pattern Radar
B3: Interviews test patterns, not problems. Sort by Verdict or Avg conf to find the exact hole. 'Weak' = average confidence 3 or below. 'Untouched' = nothing solved in this pattern yet.
B5: Topic | C5: Pattern | D5: Total | E5: Core | F5: Done | G5: Avg conf | H5: Verdict
B6: 01. Basics & Recursion | C6: Recursion warm-up | D6: =COUNTIFS(Master!$C$2:$C$918,$B6,Master!$D$2:$D$918,$C6) | E6: =COUNTIFS(Master!$C$2:$C$918,$B6,Master!$D$2:$D$918,$C6,Master!$G$2:$G$918,"Core") | F6: =COUNTIFS(Master!$C$2:$C$918,$B6,Master!$D$2:$D$918,$C6,Master!$J$2:$J$918,"Solved")+COUNTIFS(Master!$C$2:$C$918,$B6,Master!$D$2:$D$918,$C6,Master!$J$2:$J$918,"Mastered") | G6: =IFERROR(AVERAGEIFS(Master!$K$2:$K$918,Master!$C$2:$C$918,$B6,Master!$D$2:$D$918,$C6,Master!$K$2:$K$918,">0"),"") | H6: =IF($F6=0,"Untouched",IF($G6="","No rating",IF($G6<=3,"Weak","Solid")))
B7: 01. Basics & Recursion | C7: Divide & Conquer | D7: =COUNTIFS(Master!$C$2:$C$918,$B7,Master!$D$2:$D$918,$C7) | E7: =COUNTIFS(Master!$C$2:$C$918,$B7,Master!$D$2:$D$918,$C7,Master!$G$2:$G$918,"Core") | F7: =COUNTIFS(Master!$C$2:$C$918,$B7,Master!$D$2:$D$918,$C7,Master!$J$2:$J$918,"Solved")+COUNTIFS(Master!$C$2:$C$918,$B7,Master!$D$2:$D$918,$C7,Master!$J$2:$J$918,"Mastered") | G7: =IFERROR(AVERAGEIFS(Master!$K$2:$K$918,Master!$C$2:$C$918,$B7,Master!$D$2:$D$918,$C7,Master!$K$2:$K$918,">0"),"") | H7: =IF($F7=0,"Untouched",IF($G7="","No rating",IF($G7<=3,"Weak","Solid")))
B8: 02. Arrays & Two Pointers | C8: Basics | D8: =COUNTIFS(Master!$C$2:$C$918,$B8,Master!$D$2:$D$918,$C8) | E8: =COUNTIFS(Master!$C$2:$C$918,$B8,Master!$D$2:$D$918,$C8,Master!$G$2:$G$918,"Core") | F8: =COUNTIFS(Master!$C$2:$C$918,$B8,Master!$D$2:$D$918,$C8,Master!$J$2:$J$918,"Solved")+COUNTIFS(Master!$C$2:$C$918,$B8,Master!$D$2:$D$918,$C8,Master!$J$2:$J$918,"Mastered") | G8: =IFERROR(AVERAGEIFS(Master!$K$2:$K$918,Master!$C$2:$C$918,$B8,Master!$D$2:$D$918,$C8,Master!$K$2:$K$918,">0"),"") | H8: =IF($F8=0,"Untouched",IF($G8="","No rating",IF($G8<=3,"Weak","Solid")))
B9: 02. Arrays & Two Pointers | C9: Two pointers | D9: =COUNTIFS(Master!$C$2:$C$918,$B9,Master!$D$2:$D$918,$C9) | E9: =COUNTIFS(Master!$C$2:$C$918,$B9,Master!$D$2:$D$918,$C9,Master!$G$2:$G$918,"Core") | F9: =COUNTIFS(Master!$C$2:$C$918,$B9,Master!$D$2:$D$918,$C9,Master!$J$2:$J$918,"Solved")+COUNTIFS(Master!$C$2:$C$918,$B9,Master!$D$2:$D$918,$C9,Master!$J$2:$J$918,"Mastered") | G9: =IFERROR(AVERAGEIFS(Master!$K$2:$K$918,Master!$C$2:$C$918,$B9,Master!$D$2:$D$918,$C9,Master!$K$2:$K$918,">0"),"") | H9: =IF($F9=0,"Untouched",IF($G9="","No rating",IF($G9<=3,"Weak","Solid")))
B10: 02. Arrays & Two Pointers | C10: Dutch National Flag | D10: =COUNTIFS(Master!$C$2:$C$918,$B10,Master!$D$2:$D$918,$C10) | E10: =COUNTIFS(Master!$C$2:$C$918,$B10,Master!$D$2:$D$918,$C10,Master!$G$2:$G$918,"Core") | F10: =COUNTIFS(Master!$C$2:$C$918,$B10,Master!$D$2:$D$918,$C10,Master!$J$2:$J$918,"Solved")+COUNTIFS(Master!$C$2:$C$918,$B10,Master!$D$2:$D$918,$C10,Master!$J$2:$J$918,"Mastered") | G10: =IFERROR(AVERAGEIFS(Master!$K$2:$K$918,Master!$C$2:$C$918,$B10,Master!$D$2:$D$918,$C10,Master!$K$2:$K$918,">0"),"") | H10: =IF($F10=0,"Untouched",IF($G10="","No rating",IF($G10<=3,"Weak","Solid")))
B11: 02. Arrays & Two Pointers | C11: Frequency scan | D11: =COUNTIFS(Master!$C$2:$C$918,$B11,Master!$D$2:$D$918,$C11) | E11: =COUNTIFS(Master!$C$2:$C$918,$B11,Master!$D$2:$D$918,$C11,Master!$G$2:$G$918,"Core") | F11: =COUNTIFS(Master!$C$2:$C$918,$B11,Master!$D$2:$D$918,$C11,Master!$J$2:$J$918,"Solved")+COUNTIFS(Master!$C$2:$C$918,$B11,Master!$D$2:$D$918,$C11,Master!$J$2:$J$918,"Mastered") | G11: =IFERROR(AVERAGEIFS(Master!$K$2:$K$918,Master!$C$2:$C$918,$B11,Master!$D$2:$D$918,$C11,Master!$K$2:$K$918,">0"),"") | H11: =IF($F11=0,"Untouched",IF($G11="","No rating",IF($G11<=3,"Weak","Solid")))
B12: 02. Arrays & Two Pointers | C12: Voting / counting | D12: =COUNTIFS(Master!$C$2:$C$918,$B12,Master!$D$2:$D$918,$C12) | E12: =COUNTIFS(Master!$C$2:$C$918,$B12,Master!$D$2:$D$918,$C12,Master!$G$2:$G$918,"Core") | F12: =COUNTIFS(Master!$C$2:$C$918,$B12,Master!$D$2:$D$918,$C12,Master!$J$2:$J$918,"Solved")+COUNTIFS(Master!$C$2:$C$918,$B12,Master!$D$2:$D$918,$C12,Master!$J$2:$J$918,"Mastered") | G12: =IFERROR(AVERAGEIFS(Master!$K$2:$K$918,Master!$C$2:$C$918,$B12,Master!$D$2:$D$918,$C12,Master!$K$2:$K$918,">0"),"") | H12: =IF($F12=0,"Untouched",IF($G12="","No rating",IF($G12<=3,"Weak","Solid")))
B13: 02. Arrays & Two Pointers | C13: Rearrangement | D13: =COUNTIFS(Master!$C$2:$C$918,$B13,Master!$D$2:$D$918,$C13) | E13: =COUNTIFS(Master!$C$2:$C$918,$B13,Master!$D$2:$D$918,$C13,Master!$G$2:$G$918,"Core") | F13: =COUNTIFS(Master!$C$2:$C$918,$B13,Master!$D$2:$D$918,$C13,Master!$J$2:$J$918,"Solved")+COUNTIFS(Master!$C$2:$C$918,$B13,Master!$D$2:$D$918,$C13,Master!$J$2:$J$918,"Mastered") | G13: =IFERROR(AVERAGEIFS(Master!$K$2:$K$918,Master!$C$2:$C$918,$B13,Master!$D$2:$D$918,$C13,Master!$K$2:$K$918,">0"),"") | H13: =IF($F13=0,"Untouched",IF($G13="","No rating",IF($G13<=3,"Weak","Solid")))
B14: 02. Arrays & Two Pointers | C14: K-Sum | D14: =COUNTIFS(Master!$C$2:$C$918,$B14,Master!$D$2:$D$918,$C14) | E14: =COUNTIFS(Master!$C$2:$C$918,$B14,Master!$D$2:$D$918,$C14,Master!$G$2:$G$918,"Core") | F14: =COUNTIFS(Master!$C$2:$C$918,$B14,Master!$D$2:$D$918,$C14,Master!$J$2:$J$918,"Solved")+COUNTIFS(Master!$C$2:$C$918,$B14,Master!$D$2:$D$918,$C14,Master!$J$2:$J$918,"Mastered") | G14: =IFERROR(AVERAGEIFS(Master!$K$2:$K$918,Master!$C$2:$C$918,$B14,Master!$D$2:$D$918,$C14,Master!$K$2:$K$918,">0"),"") | H14: =IF($F14=0,"Untouched",IF($G14="","No rating",IF($G14<=3,"Weak","Solid")))
B15: 03. Sorting & Cyclic Sort | C15: Custom comparator | D15: =COUNTIFS(Master!$C$2:$C$918,$B15,Master!$D$2:$D$918,$C15) | E15: =COUNTIFS(Master!$C$2:$C$918,$B15,Master!$D$2:$D$918,$C15,Master!$G$2:$G$918,"Core") | F15: =COUNTIFS(Master!$C$2:$C$918,$B15,Master!$D$2:$D$918,$C15,Master!$J$2:$J$918,"Solved")+COUNTIFS(Master!$C$2:$C$918,$B15,Master!$D$2:$D$918,$C15,Master!$J$2:$J$918,"Mastered") | G15: =IFERROR(AVERAGEIFS(Master!$K$2:$K$918,Master!$C$2:$C$918,$B15,Master!$D$2:$D$918,$C15,Master!$K$2:$K$918,">0"),"") | H15: =IF($F15=0,"Untouched",IF($G15="","No rating",IF($G15<=3,"Weak","Solid")))
B16: 03. Sorting & Cyclic Sort | C16: Counting sort | D16: =COUNTIFS(Master!$C$2:$C$918,$B16,Master!$D$2:$D$918,$C16) | E16: =COUNTIFS(Master!$C$2:$C$918,$B16,Master!$D$2:$D$918,$C16,Master!$G$2:$G$918,"Core") | F16: =COUNTIFS(Master!$C$2:$C$918,$B16,Master!$D$2:$D$918,$C16,Master!$J$2:$J$918,"Solved")+COUNTIFS(Master!$C$2:$C$918,$B16,Master!$D$2:$D$918,$C16,Master!$J$2:$J$918,"Mastered") | G16: =IFERROR(AVERAGEIFS(Master!$K$2:$K$918,Master!$C$2:$C$918,$B16,Master!$D$2:$D$918,$C16,Master!$K$2:$K$918,">0"),"") | H16: =IF($F16=0,"Untouched",IF($G16="","No rating",IF($G16<=3,"Weak","Solid")))
B17: 03. Sorting & Cyclic Sort | C17: Cyclic sort | D17: =COUNTIFS(Master!$C$2:$C$918,$B17,Master!$D$2:$D$918,$C17) | E17: =COUNTIFS(Master!$C$2:$C$918,$B17,Master!$D$2:$D$918,$C17,Master!$G$2:$G$918,"Core") | F17: =COUNTIFS(Master!$C$2:$C$918,$B17,Master!$D$2:$D$918,$C17,Master!$J$2:$J$918,"Solved")+COUNTIFS(Master!$C$2:$C$918,$B17,Master!$D$2:$D$918,$C17,Master!$J$2:$J$918,"Mastered") | G17: =IFERROR(AVERAGEIFS(Master!$K$2:$K$918,Master!$C$2:$C$918,$B17,Master!$D$2:$D$918,$C17,Master!$K$2:$K$918,">0"),"") | H17: =IF($F17=0,"Untouched",IF($G17="","No rating",IF($G17<=3,"Weak","Solid")))
... B177: 21. Dynamic Programming | C177: Bitmask DP | D177: =COUNTIFS(Master!$C$2:$C$918,$B177,Master!$D$2:$D$918,$C177) | E177: =COUNTIFS(Master!$C$2:$C$918,$B177,Master!$D$2:$D$918,$C177,Master!$G$2:$G$918,"Core") | F177: =COUNTIFS(Master!$C$2:$C$918,$B177,Master!$D$2:$D$918,$C177,Master!$J$2:$J$918,"Solved")+COUNTIFS(Master!$C$2:$C$918,$B177,Master!$D$2:$D$918,$C177,Master!$J$2:$J$918,"Mastered") | G177: =IFERROR(AVERAGEIFS(Master!$K$2:$K$918,Master!$C$2:$C$918,$B177,Master!$D$2:$D$918,$C177,Master!$K$2:$K$918,">0"),"") | H177: =IF($F177=0,"Untouched",IF($G177="","No rating",IF($G177<=3,"Weak","Solid")))

Sheet Pattern Coverage
A1: Topic | B1: Pattern | C1: Core | D1: Depth | E1: Stretch
A2: 01. Basics & Recursion | B2: Recursion warm-up | C2: 10 | D2: 0 | E2: 0
A3: 01. Basics & Recursion | B3: Divide & Conquer | C3: 4 | D3: 0 | E3: 0
A4: 02. Arrays & Two Pointers | B4: Basics | C4: 3 | D4: 0 | E4: 0
A5: 02. Arrays & Two Pointers | B5: Two pointers | C5: 4 | D5: 10 | E5: 1
A6: 02. Arrays & Two Pointers | B6: Dutch National Flag | C6: 2 | D6: 2 | E6: 0
A7: 02. Arrays & Two Pointers | B7: Frequency scan | C7: 2 | D7: 0 | E7: 0
A8: 02. Arrays & Two Pointers | B8: Voting / counting | C8: 2 | D8: 0 | E8: 0
A9: 02. Arrays & Two Pointers | B9: Rearrangement | C9: 2 | D9: 3 | E9: 0
A10: 02. Arrays & Two Pointers | B10: K-Sum | C10: 3 | D10: 2 | E10: 0
A11: 03. Sorting & Cyclic Sort | B11: Custom comparator | C11: 3 | D11: 2 | E11: 0
A12: 03. Sorting & Cyclic Sort | B12: Counting sort | C12: 4 | D12: 1 | E12: 0
A13: 03. Sorting & Cyclic Sort | B13: Cyclic sort | C13: 2 | D13: 3 | E13: 1
... A173: 21. Dynamic Programming | B173: Bitmask DP | C173: 0 | D173: 0 | E173: 5
